[
null,
{"id":1,"expanded":false,"name":"Sandbox Gianna Castle","order":1,"parentId":0,"scrollX":819,"scrollY":453},
{"id":2,"expanded":true,"name":"Gianna Castle Hallway","order":2,"parentId":1,"scrollX":983,"scrollY":453},
{"id":3,"expanded":false,"name":"Gianna Castle Forest","order":3,"parentId":1,"scrollX":819,"scrollY":461},
{"id":4,"expanded":false,"name":"Gianna Castle Rokkas","order":4,"parentId":1,"scrollX":819,"scrollY":461},
{"id":5,"expanded":false,"name":"Gianna Castle Tabnath","order":5,"parentId":1,"scrollX":832,"scrollY":640},
{"id":6,"expanded":false,"name":"Gianna Castle Sea Market","order":6,"parentId":1,"scrollX":819,"scrollY":461},
{"id":7,"expanded":true,"name":"Gianna Castle Tower","order":7,"parentId":1,"scrollX":832,"scrollY":640},
{"id":8,"expanded":false,"name":"Gianna Castle Gallery","order":8,"parentId":1,"scrollX":832,"scrollY":640},
{"id":9,"expanded":false,"name":"Gianna Castle Chateau","order":9,"parentId":1,"scrollX":819,"scrollY":461},
{"id":10,"expanded":false,"name":"Gianna Castle Circus","order":10,"parentId":1,"scrollX":832,"scrollY":640},
{"id":11,"expanded":false,"name":"Gianna Castle Cathedral","order":11,"parentId":1,"scrollX":819,"scrollY":461},
{"id":12,"expanded":false,"name":"Gianna Castle Alisha's","order":12,"parentId":1,"scrollX":819,"scrollY":461},
{"id":13,"expanded":false,"name":"Gianna Castle Laboratory","order":13,"parentId":1,"scrollX":819,"scrollY":461},
{"id":14,"expanded":false,"name":"Gianna Castle Dreadnaught","order":14,"parentId":1,"scrollX":832,"scrollY":640},
{"id":15,"expanded":false,"name":"Gianna Castle Spire","order":15,"parentId":1,"scrollX":832,"scrollY":640},
{"id":16,"expanded":false,"name":"Forest Cabin","order":16,"parentId":1,"scrollX":832,"scrollY":640},
{"id":17,"expanded":false,"name":"Gianna Castle","order":56,"parentId":0,"scrollX":819,"scrollY":453},
{"id":18,"expanded":true,"name":"Throne Room","order":57,"parentId":17,"scrollX":819,"scrollY":453},
{"id":19,"expanded":true,"name":"Stairwell","order":59,"parentId":17,"scrollX":819,"scrollY":453},
{"id":20,"expanded":true,"name":"Gianna Castle","order":62,"parentId":17,"scrollX":819,"scrollY":461},
{"id":21,"expanded":true,"name":"Courtyard","order":64,"parentId":17,"scrollX":819,"scrollY":461},
{"id":22,"expanded":true,"name":"Gianna Plaza","order":65,"parentId":17,"scrollX":1445,"scrollY":445},
{"id":23,"expanded":true,"name":"Weapons Shop","order":67,"parentId":22,"scrollX":819,"scrollY":461},
{"id":24,"expanded":true,"name":"Armor Shop","order":66,"parentId":22,"scrollX":819,"scrollY":453},
{"id":25,"expanded":true,"name":"Items Shop","order":68,"parentId":22,"scrollX":819,"scrollY":461},
{"id":26,"expanded":true,"name":"Rarities Shop","order":69,"parentId":22,"scrollX":819,"scrollY":461},
{"id":27,"expanded":true,"name":"Gatehouse","order":105,"parentId":22,"scrollX":819,"scrollY":461},
{"id":28,"expanded":true,"name":"Moat","order":106,"parentId":22,"scrollX":819,"scrollY":461},
{"id":29,"expanded":false,"name":"Bordertown","order":107,"parentId":0,"scrollX":819,"scrollY":461},
{"id":30,"expanded":true,"name":"South Bordertown","order":108,"parentId":29,"scrollX":819,"scrollY":461},
{"id":31,"expanded":true,"name":"SW Bordertown","order":109,"parentId":29,"scrollX":819,"scrollY":461},
{"id":32,"expanded":true,"name":"NW Bordertown","order":110,"parentId":29,"scrollX":819,"scrollY":461},
{"id":33,"expanded":true,"name":"North Bordertown","order":111,"parentId":29,"scrollX":819,"scrollY":461},
{"id":34,"expanded":true,"name":"NE Bordertown","order":112,"parentId":29,"scrollX":819,"scrollY":461},
{"id":35,"expanded":true,"name":"SE Bordertown","order":114,"parentId":29,"scrollX":819,"scrollY":461},
{"id":36,"expanded":true,"name":"West Road","order":115,"parentId":29,"scrollX":819,"scrollY":461},
{"id":37,"expanded":true,"name":"East Road","order":117,"parentId":29,"scrollX":819,"scrollY":461},
{"id":38,"expanded":true,"name":"North Road","order":116,"parentId":29,"scrollX":832,"scrollY":640},
{"id":39,"expanded":false,"name":"Rokkas Plains","order":119,"parentId":0,"scrollX":819,"scrollY":461},
{"id":40,"expanded":true,"name":"Sea Market Road 1","order":120,"parentId":39,"scrollX":819,"scrollY":461},
{"id":41,"expanded":true,"name":"Sea Market Road 2","order":121,"parentId":39,"scrollX":819,"scrollY":461},
{"id":42,"expanded":true,"name":"Sea Market Road 3","order":123,"parentId":39,"scrollX":819,"scrollY":461},
{"id":43,"expanded":true,"name":"Great Plain","order":124,"parentId":39,"scrollX":811,"scrollY":747},
{"id":44,"expanded":false,"name":"Sea Market","order":147,"parentId":0,"scrollX":819,"scrollY":461},
{"id":45,"expanded":true,"name":"Outer Gates","order":148,"parentId":44,"scrollX":1092,"scrollY":614.6666666666666},
{"id":46,"expanded":true,"name":"Mystic's Tent","order":125,"parentId":43,"scrollX":819,"scrollY":461},
{"id":47,"expanded":true,"name":"New Rokkas Road 1","order":127,"parentId":39,"scrollX":819,"scrollY":461},
{"id":48,"expanded":true,"name":"New Rokkas Road 2","order":128,"parentId":39,"scrollX":819,"scrollY":461},
{"id":49,"expanded":true,"name":"New Rokkas Road 3","order":129,"parentId":39,"scrollX":832,"scrollY":640},
{"id":50,"expanded":true,"name":"New Rokkas Road 4","order":130,"parentId":39,"scrollX":819,"scrollY":461},
{"id":51,"expanded":true,"name":"West Plains 1","order":131,"parentId":39,"scrollX":819,"scrollY":461},
{"id":52,"expanded":true,"name":"West Plains 2","order":133,"parentId":39,"scrollX":819,"scrollY":461},
{"id":53,"expanded":true,"name":"West Plains 3","order":134,"parentId":39,"scrollX":819,"scrollY":461},
{"id":54,"expanded":true,"name":"West Plains 4","order":135,"parentId":39,"scrollX":819,"scrollY":461},
{"id":55,"expanded":true,"name":"West Plains 5","order":136,"parentId":39,"scrollX":832,"scrollY":640},
{"id":56,"expanded":true,"name":"West Plains 6","order":137,"parentId":39,"scrollX":819,"scrollY":461},
{"id":57,"expanded":true,"name":"West Plains 7","order":138,"parentId":39,"scrollX":819,"scrollY":461},
{"id":58,"expanded":true,"name":"West Plains 8","order":139,"parentId":39,"scrollX":2808,"scrollY":1580.5714285714284},
{"id":59,"expanded":true,"name":"West Plains 9","order":140,"parentId":39,"scrollX":819,"scrollY":461},
{"id":60,"expanded":false,"name":"Kepiat Gallery","order":161,"parentId":0,"scrollX":819,"scrollY":461},
{"id":61,"expanded":true,"name":"Gianna Forest","order":181,"parentId":0,"scrollX":819,"scrollY":461},
{"id":62,"expanded":false,"name":"New Rokkas","order":245,"parentId":0,"scrollX":819,"scrollY":461},
{"id":63,"expanded":false,"name":"Cathedral of the Spirit","order":278,"parentId":0,"scrollX":819,"scrollY":461},
{"id":64,"expanded":false,"name":"Forsaken Tower","order":319,"parentId":0,"scrollX":819,"scrollY":461},
{"id":65,"expanded":false,"name":"Bura's Travelling Circus","order":345,"parentId":0,"scrollX":819,"scrollY":461},
{"id":66,"expanded":true,"name":"East Plains 1","order":141,"parentId":39,"scrollX":832,"scrollY":640},
{"id":67,"expanded":true,"name":"East Plains 2","order":142,"parentId":39,"scrollX":819,"scrollY":461},
{"id":68,"expanded":true,"name":"East Plains 3","order":143,"parentId":39,"scrollX":819,"scrollY":461},
{"id":69,"expanded":true,"name":"East Plains 4 (Circus)","order":144,"parentId":39,"scrollX":819,"scrollY":461},
{"id":70,"expanded":true,"name":"East Plains 5","order":145,"parentId":39,"scrollX":832,"scrollY":640},
{"id":71,"expanded":true,"name":"East Plains 6","order":146,"parentId":39,"scrollX":819,"scrollY":461},
{"id":72,"expanded":true,"name":"Sea Market Front","order":149,"parentId":44,"scrollX":819,"scrollY":461},
{"id":73,"expanded":true,"name":"SW Sea Market","order":150,"parentId":44,"scrollX":819,"scrollY":461},
{"id":74,"expanded":true,"name":"NW Sea Market","order":151,"parentId":44,"scrollX":478,"scrollY":448.5},
{"id":75,"expanded":true,"name":"South Sea Market","order":152,"parentId":44,"scrollX":819,"scrollY":461},
{"id":76,"expanded":true,"name":"SE Sea Market","order":153,"parentId":44,"scrollX":819,"scrollY":461},
{"id":77,"expanded":true,"name":"NE Sea Market","order":154,"parentId":44,"scrollX":478,"scrollY":448.5},
{"id":78,"expanded":true,"name":"Auction Plaza","order":155,"parentId":44,"scrollX":819,"scrollY":461},
{"id":79,"expanded":true,"name":"Docks","order":156,"parentId":44,"scrollX":1092,"scrollY":614.6666666666666},
{"id":80,"expanded":true,"name":"Mayoress' Manor 1F","order":157,"parentId":44,"scrollX":819,"scrollY":461},
{"id":81,"expanded":true,"name":"Mayoress' Manor 2F","order":159,"parentId":44,"scrollX":819,"scrollY":461},
{"id":82,"expanded":true,"name":"Sea Market Back","order":160,"parentId":44,"scrollX":819,"scrollY":461},
{"id":83,"expanded":true,"name":"Public Gallery 1","order":162,"parentId":60,"scrollX":819,"scrollY":461},
{"id":84,"expanded":true,"name":"Public Gallery 2","order":163,"parentId":60,"scrollX":819,"scrollY":461},
{"id":85,"expanded":true,"name":"Public Gallery 3","order":164,"parentId":60,"scrollX":819,"scrollY":461},
{"id":86,"expanded":true,"name":"Mayoress' Manor Hidden Room","order":158,"parentId":80,"scrollX":819,"scrollY":461},
{"id":87,"expanded":true,"name":"Forest Road 1","order":183,"parentId":96,"scrollX":819,"scrollY":453},
{"id":88,"expanded":true,"name":"Forest Road 2","order":184,"parentId":96,"scrollX":832,"scrollY":640},
{"id":89,"expanded":true,"name":"Cabin Entrance","order":186,"parentId":96,"scrollX":819,"scrollY":461},
{"id":90,"expanded":true,"name":"Forest Cabin","order":187,"parentId":89,"scrollX":811,"scrollY":499},
{"id":91,"expanded":true,"name":"Forest Road 5","order":191,"parentId":96,"scrollX":819,"scrollY":461},
{"id":92,"expanded":true,"name":"Forest Road 6","order":192,"parentId":96,"scrollX":819,"scrollY":461},
{"id":93,"expanded":true,"name":"Forest Road 4","order":190,"parentId":96,"scrollX":819,"scrollY":461},
{"id":94,"expanded":true,"name":"Forest Road 7 (Cathedral)","order":193,"parentId":96,"scrollX":832,"scrollY":640},
{"id":95,"expanded":true,"name":"Cathedral Entrance","order":280,"parentId":276,"scrollX":811,"scrollY":461},
{"id":96,"expanded":true,"name":"Southern Forest","order":182,"parentId":61,"scrollX":819,"scrollY":461},
{"id":97,"expanded":true,"name":"Cathedral Forest 1","order":194,"parentId":96,"scrollX":832,"scrollY":640},
{"id":98,"expanded":true,"name":"Cathedral Forest 2","order":195,"parentId":96,"scrollX":832,"scrollY":640},
{"id":99,"expanded":true,"name":"Cathedral Forest 3","order":196,"parentId":98,"scrollX":832,"scrollY":640},
{"id":100,"expanded":true,"name":"Southern Forest 1","order":197,"parentId":96,"scrollX":832,"scrollY":640},
{"id":101,"expanded":true,"name":"Southern Forest 2","order":198,"parentId":96,"scrollX":478,"scrollY":448.5},
{"id":102,"expanded":true,"name":"Southern Forest 3","order":199,"parentId":96,"scrollX":819,"scrollY":461},
{"id":103,"expanded":true,"name":"Southern Forest 4","order":200,"parentId":96,"scrollX":832,"scrollY":640},
{"id":104,"expanded":true,"name":"Southern Forest 5","order":201,"parentId":96,"scrollX":819,"scrollY":461},
{"id":105,"expanded":true,"name":"Southern Forest 6","order":202,"parentId":96,"scrollX":478,"scrollY":448.5},
{"id":106,"expanded":true,"name":"Southern Forest 7","order":203,"parentId":96,"scrollX":819,"scrollY":461},
{"id":107,"expanded":true,"name":"Southern Forest 8","order":205,"parentId":96,"scrollX":819,"scrollY":461},
{"id":108,"expanded":true,"name":"Southern Forest 9","order":206,"parentId":96,"scrollX":819,"scrollY":461},
{"id":109,"expanded":true,"name":"Southern Forest 10","order":207,"parentId":96,"scrollX":819,"scrollY":461},
{"id":110,"expanded":true,"name":"Southern Forest 11","order":208,"parentId":96,"scrollX":832,"scrollY":640},
{"id":111,"expanded":true,"name":"Julia's Office","order":113,"parentId":34,"scrollX":819,"scrollY":461},
{"id":112,"expanded":true,"name":"Forest Road 3","order":185,"parentId":88,"scrollX":819,"scrollY":461},
{"id":113,"expanded":true,"name":"Tower Forest","order":209,"parentId":61,"scrollX":819,"scrollY":461},
{"id":114,"expanded":true,"name":"Tower Entrance","order":210,"parentId":113,"scrollX":819,"scrollY":461},
{"id":115,"expanded":true,"name":"Tower Forest 1","order":211,"parentId":113,"scrollX":819,"scrollY":461},
{"id":116,"expanded":true,"name":"Tower Forest 2","order":213,"parentId":113,"scrollX":819,"scrollY":461},
{"id":117,"expanded":true,"name":"Tower Forest 3","order":214,"parentId":113,"scrollX":819,"scrollY":461},
{"id":118,"expanded":true,"name":"Tower Forest 4","order":215,"parentId":113,"scrollX":811,"scrollY":456.5},
{"id":119,"expanded":true,"name":"Tower Forest 5","order":216,"parentId":113,"scrollX":832,"scrollY":640},
{"id":120,"expanded":true,"name":"Tower Forest 6","order":217,"parentId":113,"scrollX":819,"scrollY":461},
{"id":121,"expanded":true,"name":"Tower Forest 7","order":218,"parentId":113,"scrollX":819,"scrollY":461},
{"id":122,"expanded":true,"name":"Tower Forest 8","order":219,"parentId":113,"scrollX":819,"scrollY":461},
{"id":123,"expanded":true,"name":"Tower Forest 9","order":220,"parentId":113,"scrollX":819,"scrollY":461},
{"id":124,"expanded":true,"name":"Tower Forest 10","order":221,"parentId":113,"scrollX":819,"scrollY":461},
{"id":125,"expanded":true,"name":"Tower Forest 11","order":222,"parentId":113,"scrollX":819,"scrollY":461},
{"id":126,"expanded":true,"name":"Tower Forest 12","order":223,"parentId":113,"scrollX":832,"scrollY":640},
{"id":127,"expanded":true,"name":"Tower Forest 13","order":224,"parentId":113,"scrollX":478,"scrollY":448.5},
{"id":128,"expanded":true,"name":"Tower Forest 14","order":225,"parentId":113,"scrollX":819,"scrollY":461},
{"id":129,"expanded":true,"name":"Tower Forest 15","order":226,"parentId":113,"scrollX":819,"scrollY":461},
{"id":130,"expanded":true,"name":"Forest Edge North","order":227,"parentId":113,"scrollX":819,"scrollY":461},
{"id":131,"expanded":true,"name":"Forest Edge East","order":228,"parentId":113,"scrollX":819,"scrollY":461},
{"id":132,"expanded":true,"name":"Hall of Orbs","order":63,"parentId":20,"scrollX":819,"scrollY":461},
{"id":133,"expanded":true,"name":"Forsaken Tower Floor 1","order":320,"parentId":64,"scrollX":811,"scrollY":787},
{"id":134,"expanded":true,"name":"Northern Forest","order":229,"parentId":61,"scrollX":819,"scrollY":461},
{"id":135,"expanded":true,"name":"Northern Forest 1","order":230,"parentId":134,"scrollX":832,"scrollY":640},
{"id":136,"expanded":true,"name":"Northern Forest 2","order":231,"parentId":134,"scrollX":832,"scrollY":640},
{"id":137,"expanded":true,"name":"Northern Forest 3","order":232,"parentId":134,"scrollX":819,"scrollY":461},
{"id":138,"expanded":true,"name":"Northern Forest 4","order":233,"parentId":134,"scrollX":832,"scrollY":640},
{"id":139,"expanded":true,"name":"Northern Forest 5","order":234,"parentId":134,"scrollX":832,"scrollY":640},
{"id":140,"expanded":true,"name":"Northern Forest 6","order":235,"parentId":134,"scrollX":832,"scrollY":640},
{"id":141,"expanded":true,"name":"Northern Forest 7","order":236,"parentId":134,"scrollX":832,"scrollY":640},
{"id":142,"expanded":true,"name":"Northern Forest 8","order":237,"parentId":134,"scrollX":819,"scrollY":461},
{"id":143,"expanded":true,"name":"Northern Forest 9","order":238,"parentId":134,"scrollX":819,"scrollY":461},
{"id":144,"expanded":true,"name":"Northern Forest 10","order":239,"parentId":134,"scrollX":819,"scrollY":461},
{"id":145,"expanded":true,"name":"Northern Forest 11","order":240,"parentId":134,"scrollX":819,"scrollY":461},
{"id":146,"expanded":true,"name":"Northern Forest 12","order":241,"parentId":134,"scrollX":819,"scrollY":461},
{"id":147,"expanded":true,"name":"Northern Forest 13","order":242,"parentId":134,"scrollX":819,"scrollY":461},
{"id":148,"expanded":true,"name":"Northern Forest 14","order":243,"parentId":134,"scrollX":832,"scrollY":640},
{"id":149,"expanded":true,"name":"Uphill Path","order":244,"parentId":134,"scrollX":819,"scrollY":461},
{"id":150,"expanded":false,"name":"Alisha's House","order":430,"parentId":0,"scrollX":819,"scrollY":461},
{"id":151,"expanded":true,"name":"Front Door","order":432,"parentId":278,"scrollX":819,"scrollY":461},
{"id":152,"expanded":false,"name":"Living Room","order":433,"parentId":278,"scrollX":819,"scrollY":461},
{"id":153,"expanded":false,"name":"Kitchen","order":434,"parentId":278,"scrollX":832,"scrollY":640},
{"id":154,"expanded":true,"name":"Bedroom","order":436,"parentId":278,"scrollX":478,"scrollY":448.5},
{"id":155,"expanded":false,"name":"Bedroom (Open)","order":437,"parentId":154,"scrollX":819,"scrollY":461},
{"id":156,"expanded":false,"name":"Backyard","order":435,"parentId":278,"scrollX":338,"scrollY":448.5},
{"id":157,"expanded":false,"name":"Alisha's Basement","order":439,"parentId":279,"scrollX":338,"scrollY":448.5},
{"id":158,"expanded":true,"name":"Ticket Booth","order":346,"parentId":65,"scrollX":819,"scrollY":461},
{"id":159,"expanded":true,"name":"Circus Entrance","order":347,"parentId":65,"scrollX":819,"scrollY":461},
{"id":160,"expanded":false,"name":"Tabnath Mountains","order":359,"parentId":0,"scrollX":478,"scrollY":448.5},
{"id":161,"expanded":true,"name":"Middle Tabnath 1","order":360,"parentId":160,"scrollX":819,"scrollY":461},
{"id":162,"expanded":true,"name":"Middle Tabnath 2","order":361,"parentId":160,"scrollX":819,"scrollY":461},
{"id":163,"expanded":true,"name":"Middle Tabnath 3","order":363,"parentId":160,"scrollX":819,"scrollY":461},
{"id":164,"expanded":true,"name":"Chateau Entrance","order":364,"parentId":160,"scrollX":819,"scrollY":461},
{"id":165,"expanded":true,"name":"Chateau East","order":365,"parentId":160,"scrollX":819,"scrollY":461},
{"id":166,"expanded":true,"name":"West Tabnath","order":367,"parentId":160,"scrollX":2934,"scrollY":919},
{"id":167,"expanded":true,"name":"East Tabnath","order":370,"parentId":160,"scrollX":3269,"scrollY":2230},
{"id":168,"expanded":false,"name":"Game Over","order":17,"parentId":1,"scrollX":819,"scrollY":461},
{"id":169,"expanded":true,"name":"Woodrot Forest 1","order":375,"parentId":182,"scrollX":819,"scrollY":461},
{"id":170,"expanded":true,"name":"Weapon/Armor Shop","order":251,"parentId":179,"scrollX":832,"scrollY":640},
{"id":171,"expanded":true,"name":"Items Shop","order":253,"parentId":180,"scrollX":819,"scrollY":453},
{"id":172,"expanded":true,"name":"Woodrot Forest 2","order":376,"parentId":182,"scrollX":832,"scrollY":640},
{"id":173,"expanded":true,"name":"Woodrot Forest 3","order":382,"parentId":182,"scrollX":819,"scrollY":461},
{"id":174,"expanded":true,"name":"Woodrot Forest 4","order":383,"parentId":182,"scrollX":832,"scrollY":640},
{"id":175,"expanded":true,"name":"Woodrot Forest 5","order":384,"parentId":182,"scrollX":819,"scrollY":461},
{"id":176,"expanded":true,"name":"Woodrot Forest 6","order":385,"parentId":182,"scrollX":819,"scrollY":461},
{"id":177,"expanded":true,"name":"Woodrot Forest 7","order":386,"parentId":182,"scrollX":832,"scrollY":640},
{"id":178,"expanded":true,"name":"New Rokkas Entrance","order":247,"parentId":274,"scrollX":819,"scrollY":461},
{"id":179,"expanded":true,"name":"New Rokkas West","order":250,"parentId":274,"scrollX":832,"scrollY":640},
{"id":180,"expanded":true,"name":"New Rokkas East","order":252,"parentId":274,"scrollX":819,"scrollY":461},
{"id":181,"expanded":true,"name":"New Rokkas North","order":254,"parentId":274,"scrollX":819,"scrollY":461},
{"id":182,"expanded":false,"name":"Woodrot Forest","order":374,"parentId":0,"scrollX":819,"scrollY":461},
{"id":183,"expanded":false,"name":"DEMO","order":18,"parentId":1,"scrollX":819,"scrollY":453},
{"id":184,"expanded":false,"name":"DEMO Basement","order":19,"parentId":1,"scrollX":819,"scrollY":461},
{"id":185,"expanded":true,"name":"Woodrot Forest 8","order":387,"parentId":182,"scrollX":832,"scrollY":640},
{"id":186,"expanded":true,"name":"Tinkly's Spring","order":388,"parentId":182,"scrollX":819,"scrollY":461},
{"id":187,"expanded":true,"name":"Woodrot Forest 9","order":389,"parentId":182,"scrollX":832,"scrollY":640},
{"id":188,"expanded":true,"name":"Woodrot Forest 10","order":390,"parentId":182,"scrollX":832,"scrollY":640},
{"id":189,"expanded":true,"name":"Woodrot Forest 11 (To Beach)","order":391,"parentId":182,"scrollX":819,"scrollY":461},
{"id":190,"expanded":true,"name":"Woodrot Forest 12","order":392,"parentId":182,"scrollX":832,"scrollY":640},
{"id":191,"expanded":true,"name":"Woodrot Forest 13","order":393,"parentId":182,"scrollX":832,"scrollY":640},
{"id":192,"expanded":true,"name":"Woodrot Forest 14","order":394,"parentId":182,"scrollX":832,"scrollY":640},
{"id":193,"expanded":true,"name":"Rokkas Stadium","order":258,"parentId":62,"scrollX":832,"scrollY":640},
{"id":194,"expanded":true,"name":"Rokkas Slut Bar","order":269,"parentId":62,"scrollX":811,"scrollY":453},
{"id":195,"expanded":false,"name":"Gianna Castle Mist","order":20,"parentId":1,"scrollX":819,"scrollY":461},
{"id":196,"expanded":true,"name":"Woodrot Forest 15","order":395,"parentId":182,"scrollX":819,"scrollY":461},
{"id":197,"expanded":true,"name":"Woodrot Forest 16","order":396,"parentId":182,"scrollX":832,"scrollY":640},
{"id":198,"expanded":true,"name":"Woodrot Forest 17","order":397,"parentId":182,"scrollX":832,"scrollY":640},
{"id":199,"expanded":true,"name":"Woodrot Forest 18","order":398,"parentId":182,"scrollX":819,"scrollY":461},
{"id":200,"expanded":true,"name":"Woodrot Forest 19","order":399,"parentId":182,"scrollX":832,"scrollY":640},
{"id":201,"expanded":true,"name":"Woodrot Forest 20","order":400,"parentId":182,"scrollX":819,"scrollY":461},
{"id":202,"expanded":true,"name":"Woodrot Forest 21","order":401,"parentId":182,"scrollX":832,"scrollY":640},
{"id":203,"expanded":true,"name":"Woodrot Forest 22","order":402,"parentId":182,"scrollX":832,"scrollY":640},
{"id":204,"expanded":true,"name":"Woodrot Forest 25","order":405,"parentId":182,"scrollX":832,"scrollY":640},
{"id":205,"expanded":true,"name":"Woodrot Forest 23","order":403,"parentId":182,"scrollX":478,"scrollY":448.5},
{"id":206,"expanded":true,"name":"Woodrot Forest 24","order":404,"parentId":182,"scrollX":832,"scrollY":640},
{"id":207,"expanded":true,"name":"Woodrot Forest 26","order":406,"parentId":182,"scrollX":819,"scrollY":461},
{"id":208,"expanded":true,"name":"Woodrot Forest 27 (Cabin)","order":407,"parentId":182,"scrollX":819,"scrollY":461},
{"id":209,"expanded":true,"name":"Woodrot Forest 28","order":408,"parentId":182,"scrollX":832,"scrollY":640},
{"id":210,"expanded":true,"name":"Woodrot Forest 29","order":409,"parentId":182,"scrollX":832,"scrollY":640},
{"id":211,"expanded":true,"name":"Woodrot Forest 30","order":410,"parentId":182,"scrollX":819,"scrollY":461},
{"id":212,"expanded":true,"name":"Woodrot Forest 31","order":411,"parentId":182,"scrollX":832,"scrollY":640},
{"id":213,"expanded":true,"name":"Woodrot Forest 32","order":412,"parentId":182,"scrollX":478,"scrollY":448.5},
{"id":214,"expanded":true,"name":"Woodrot Forest 33","order":413,"parentId":182,"scrollX":832,"scrollY":640},
{"id":215,"expanded":true,"name":"Secret Lab Entrance","order":414,"parentId":182,"scrollX":819,"scrollY":461},
{"id":216,"expanded":true,"name":"Woodrot Forest 34","order":415,"parentId":182,"scrollX":819,"scrollY":461},
{"id":217,"expanded":true,"name":"Woodrot Forest 35","order":417,"parentId":182,"scrollX":832,"scrollY":640},
{"id":218,"expanded":true,"name":"Woodrot Forest 36","order":418,"parentId":182,"scrollX":832,"scrollY":640},
{"id":219,"expanded":true,"name":"Woodrot Forest 37","order":419,"parentId":182,"scrollX":819,"scrollY":461},
{"id":220,"expanded":true,"name":"Woodrot Forest 38","order":420,"parentId":182,"scrollX":819,"scrollY":461},
{"id":221,"expanded":true,"name":"Woodrot Forest 39 (Witch)","order":421,"parentId":182,"scrollX":819,"scrollY":461},
{"id":222,"expanded":true,"name":"Woodrot Forest 40","order":423,"parentId":182,"scrollX":832,"scrollY":640},
{"id":223,"expanded":true,"name":"Woodrot Forest 41","order":424,"parentId":182,"scrollX":832,"scrollY":640},
{"id":224,"expanded":true,"name":"Woodrot Forest 42","order":425,"parentId":182,"scrollX":819,"scrollY":461},
{"id":225,"expanded":true,"name":"Uphill Path 1","order":426,"parentId":182,"scrollX":832,"scrollY":640},
{"id":226,"expanded":true,"name":"Uphill Path 2","order":427,"parentId":182,"scrollX":832,"scrollY":640},
{"id":227,"expanded":true,"name":"Uphill Path 3","order":428,"parentId":182,"scrollX":832,"scrollY":640},
{"id":228,"expanded":false,"name":"West Beach Outpost","order":454,"parentId":0,"scrollX":478,"scrollY":448.5},
{"id":229,"expanded":true,"name":"Outpost Gate","order":455,"parentId":228,"scrollX":832,"scrollY":640},
{"id":230,"expanded":true,"name":"Outpost Entrance","order":456,"parentId":228,"scrollX":817,"scrollY":455.5},
{"id":231,"expanded":true,"name":"Outpost North","order":459,"parentId":228,"scrollX":819,"scrollY":453},
{"id":232,"expanded":true,"name":"Outpost South","order":460,"parentId":228,"scrollX":819,"scrollY":461},
{"id":233,"expanded":true,"name":"Outpost West","order":463,"parentId":228,"scrollX":819,"scrollY":461},
{"id":234,"expanded":true,"name":"Docks","order":465,"parentId":228,"scrollX":819,"scrollY":461},
{"id":235,"expanded":false,"name":"West Beach","order":466,"parentId":0,"scrollX":819,"scrollY":461},
{"id":236,"expanded":true,"name":"Luxatep Road 1","order":467,"parentId":235,"scrollX":819,"scrollY":461},
{"id":237,"expanded":false,"name":"Tabnath","order":488,"parentId":0,"scrollX":819,"scrollY":453},
{"id":238,"expanded":true,"name":"Tabnath Entrance","order":489,"parentId":237,"scrollX":819,"scrollY":461},
{"id":239,"expanded":false,"name":"Mt. Pleasant","order":531,"parentId":0,"scrollX":819,"scrollY":461},
{"id":240,"expanded":true,"name":"Mt. Pleasant Entrance","order":532,"parentId":239,"scrollX":459,"scrollY":448.5},
{"id":241,"expanded":false,"name":"Vemix's Laboratory","order":589,"parentId":0,"scrollX":478,"scrollY":448.5},
{"id":242,"expanded":true,"name":"Environment Hallway","order":616,"parentId":241,"scrollX":1524,"scrollY":453},
{"id":243,"expanded":false,"name":"Laboratory Entrance","order":590,"parentId":241,"scrollX":819,"scrollY":461},
{"id":244,"expanded":false,"name":"Jewel Storage","order":623,"parentId":241,"scrollX":819,"scrollY":461},
{"id":245,"expanded":false,"name":"Chateau d'Yterre","order":624,"parentId":0,"scrollX":832,"scrollY":640},
{"id":246,"expanded":true,"name":"Throne Room (FE3)","order":886,"parentId":779,"scrollX":819,"scrollY":461},
{"id":247,"expanded":false,"name":"Phantom Express","order":648,"parentId":0,"scrollX":478,"scrollY":448.5},
{"id":248,"expanded":true,"name":"Caboose","order":649,"parentId":247,"scrollX":819,"scrollY":461},
{"id":249,"expanded":true,"name":"Dock","order":795,"parentId":257,"scrollX":819,"scrollY":461},
{"id":250,"expanded":false,"name":"City of Mist","order":678,"parentId":0,"scrollX":819,"scrollY":461},
{"id":251,"expanded":false,"name":"Queen's Chamber","order":679,"parentId":250,"scrollX":819,"scrollY":461},
{"id":252,"expanded":true,"name":"Train Platform","order":680,"parentId":250,"scrollX":819,"scrollY":461},
{"id":253,"expanded":false,"name":"Crashed Dreadnaught","order":731,"parentId":0,"scrollX":819,"scrollY":461},
{"id":254,"expanded":false,"name":"Wreckage Trail","order":732,"parentId":253,"scrollX":819,"scrollY":461},
{"id":255,"expanded":false,"name":"Tomb of Luxatep","order":734,"parentId":0,"scrollX":819,"scrollY":461},
{"id":256,"expanded":false,"name":"Lair of the Puppetmaster","order":765,"parentId":0,"scrollX":819,"scrollY":461},
{"id":257,"expanded":false,"name":"Castle Hargrave","order":781,"parentId":0,"scrollX":819,"scrollY":461},
{"id":258,"expanded":false,"name":"Demons' Spire","order":811,"parentId":0,"scrollX":819,"scrollY":461},
{"id":259,"expanded":true,"name":"Residential Area","order":75,"parentId":22,"scrollX":819,"scrollY":461},
{"id":260,"expanded":true,"name":"Entry","order":766,"parentId":256,"scrollX":819,"scrollY":461},
{"id":261,"expanded":true,"name":"Throne Room","order":782,"parentId":257,"scrollX":819,"scrollY":461},
{"id":262,"expanded":true,"name":"Destroyed Village","order":844,"parentId":258,"scrollX":821,"scrollY":461},
{"id":263,"expanded":false,"name":"Healing Shop","order":282,"parentId":276,"scrollX":819,"scrollY":461},
{"id":264,"expanded":false,"name":"Traveller's Shop","order":283,"parentId":276,"scrollX":819,"scrollY":461},
{"id":265,"expanded":false,"name":"Kitchen","order":284,"parentId":276,"scrollX":819,"scrollY":461},
{"id":266,"expanded":true,"name":"Secret Room","order":285,"parentId":276,"scrollX":819,"scrollY":461},
{"id":267,"expanded":false,"name":"Secret Room (Open)","order":286,"parentId":266,"scrollX":819,"scrollY":461},
{"id":268,"expanded":true,"name":"Back Room","order":287,"parentId":276,"scrollX":819,"scrollY":453},
{"id":269,"expanded":true,"name":"Descent 1 (Limbo)","order":289,"parentId":277,"scrollX":819,"scrollY":461},
{"id":270,"expanded":true,"name":"Public Gallery 3 (Broken)","order":165,"parentId":85,"scrollX":819,"scrollY":461},
{"id":271,"expanded":true,"name":"Dungeon Entry","order":166,"parentId":60,"scrollX":1092,"scrollY":614.6666666666666},
{"id":272,"expanded":true,"name":"Fairgrounds","order":349,"parentId":65,"scrollX":811,"scrollY":1327},
{"id":273,"expanded":true,"name":"Ferris Wheel","order":350,"parentId":272,"scrollX":819,"scrollY":461},
{"id":274,"expanded":true,"name":"City","order":246,"parentId":62,"scrollX":819,"scrollY":461},
{"id":275,"expanded":false,"name":"Bridge","order":733,"parentId":253,"scrollX":819,"scrollY":461},
{"id":276,"expanded":true,"name":"Cathedral","order":279,"parentId":63,"scrollX":819,"scrollY":461},
{"id":277,"expanded":true,"name":"Dungeon","order":288,"parentId":63,"scrollX":819,"scrollY":461},
{"id":278,"expanded":true,"name":"House","order":431,"parentId":150,"scrollX":819,"scrollY":461},
{"id":279,"expanded":true,"name":"Dungeon","order":438,"parentId":150,"scrollX":819,"scrollY":461},
{"id":280,"expanded":false,"name":"Stairs A","order":321,"parentId":64,"scrollX":819,"scrollY":461},
{"id":281,"expanded":false,"name":"Stairs B","order":322,"parentId":64,"scrollX":819,"scrollY":461},
{"id":282,"expanded":true,"name":"Stairs D","order":324,"parentId":64,"scrollX":819,"scrollY":461},
{"id":283,"expanded":true,"name":"Left Hall","order":325,"parentId":64,"scrollX":819,"scrollY":461},
{"id":284,"expanded":true,"name":"Stairs C","order":323,"parentId":64,"scrollX":819,"scrollY":461},
{"id":285,"expanded":false,"name":"Right Hall","order":328,"parentId":64,"scrollX":811,"scrollY":547},
{"id":286,"expanded":false,"name":"Left Hall (Open)","order":326,"parentId":283,"scrollX":811,"scrollY":453},
{"id":287,"expanded":false,"name":"Left Hall (Dead End)","order":327,"parentId":283,"scrollX":819,"scrollY":461},
{"id":288,"expanded":true,"name":"Left Upstairs 1","order":329,"parentId":64,"scrollX":811,"scrollY":461},
{"id":289,"expanded":false,"name":"Left Upstairs 2","order":330,"parentId":288,"scrollX":819,"scrollY":461},
{"id":290,"expanded":false,"name":"Left Upstairs 3","order":331,"parentId":288,"scrollX":819,"scrollY":461},
{"id":291,"expanded":true,"name":"Left Upstairs 4","order":332,"parentId":288,"scrollX":819,"scrollY":461},
{"id":292,"expanded":false,"name":"Left Upstairs 5","order":334,"parentId":288,"scrollX":819,"scrollY":461},
{"id":293,"expanded":false,"name":"Bridge Over Entry","order":336,"parentId":64,"scrollX":819,"scrollY":461},
{"id":294,"expanded":false,"name":"Room 1-1","order":290,"parentId":269,"scrollX":819,"scrollY":461},
{"id":295,"expanded":true,"name":"Right Upstairs 1","order":337,"parentId":64,"scrollX":817,"scrollY":455.5},
{"id":296,"expanded":false,"name":"Right Upstairs 2","order":338,"parentId":295,"scrollX":818,"scrollY":456.5},
{"id":297,"expanded":false,"name":"Right Upstairs 3","order":339,"parentId":295,"scrollX":478,"scrollY":448.5},
{"id":298,"expanded":false,"name":"Right Upstairs 4","order":340,"parentId":295,"scrollX":832,"scrollY":640},
{"id":299,"expanded":false,"name":"Right Upstairs 5","order":341,"parentId":295,"scrollX":819,"scrollY":461},
{"id":300,"expanded":false,"name":"Soulgem Shop","order":342,"parentId":295,"scrollX":819,"scrollY":461},
{"id":301,"expanded":false,"name":"Left Upstairs 6","order":335,"parentId":288,"scrollX":817,"scrollY":455.5},
{"id":302,"expanded":false,"name":"Hidden Room","order":333,"parentId":291,"scrollX":819,"scrollY":461},
{"id":303,"expanded":true,"name":"Boss Room 1","order":343,"parentId":64,"scrollX":819,"scrollY":461},
{"id":304,"expanded":false,"name":"Boss Room 2","order":344,"parentId":303,"scrollX":819,"scrollY":461},
{"id":305,"expanded":false,"name":"Room 1-2","order":291,"parentId":269,"scrollX":819,"scrollY":461},
{"id":306,"expanded":true,"name":"Descent 2 (Lust)","order":292,"parentId":277,"scrollX":832,"scrollY":640},
{"id":307,"expanded":false,"name":"Room 2-1","order":293,"parentId":306,"scrollX":819,"scrollY":461},
{"id":308,"expanded":false,"name":"Room 2-2","order":294,"parentId":306,"scrollX":832,"scrollY":640},
{"id":309,"expanded":false,"name":"Room 2-3","order":295,"parentId":306,"scrollX":832,"scrollY":640},
{"id":310,"expanded":true,"name":"Descent 3 (Gluttony)","order":296,"parentId":277,"scrollX":832,"scrollY":640},
{"id":311,"expanded":false,"name":"Room 3-1","order":297,"parentId":310,"scrollX":818,"scrollY":456.5},
{"id":312,"expanded":true,"name":"Descent 4 (Greed)","order":298,"parentId":277,"scrollX":819,"scrollY":461},
{"id":313,"expanded":true,"name":"Descent 5 (Wrath)","order":305,"parentId":277,"scrollX":832,"scrollY":640},
{"id":314,"expanded":true,"name":"Descent 6 (Heresy)","order":307,"parentId":277,"scrollX":832,"scrollY":640},
{"id":315,"expanded":true,"name":"Descent 7 (Violence)","order":310,"parentId":277,"scrollX":819,"scrollY":461},
{"id":316,"expanded":true,"name":"Descent 7 (Violence) (Open)","order":311,"parentId":315,"scrollX":819,"scrollY":461},
{"id":317,"expanded":true,"name":"Descent 8 (Fraud)","order":316,"parentId":277,"scrollX":819,"scrollY":461},
{"id":318,"expanded":true,"name":"Descent 9 (Betrayal)","order":318,"parentId":277,"scrollX":819,"scrollY":461},
{"id":319,"expanded":true,"name":"Descent 8 (Fraud) (Open)","order":317,"parentId":317,"scrollX":819,"scrollY":461},
{"id":320,"expanded":false,"name":"Room 4-2","order":300,"parentId":312,"scrollX":819,"scrollY":461},
{"id":321,"expanded":false,"name":"Room 4-3","order":301,"parentId":312,"scrollX":832,"scrollY":640},
{"id":322,"expanded":false,"name":"Room 4-1","order":299,"parentId":312,"scrollX":819,"scrollY":461},
{"id":323,"expanded":false,"name":"Room 4-4","order":302,"parentId":312,"scrollX":819,"scrollY":461},
{"id":324,"expanded":false,"name":"Room 4-5","order":303,"parentId":312,"scrollX":832,"scrollY":640},
{"id":325,"expanded":false,"name":"Room 4-6","order":304,"parentId":312,"scrollX":818,"scrollY":453},
{"id":326,"expanded":false,"name":"Room 5-1","order":306,"parentId":313,"scrollX":832,"scrollY":640},
{"id":327,"expanded":true,"name":"Room 6-1","order":308,"parentId":314,"scrollX":832,"scrollY":640},
{"id":328,"expanded":true,"name":"Room 7-1","order":312,"parentId":315,"scrollX":819,"scrollY":461},
{"id":329,"expanded":true,"name":"Room 7-2","order":313,"parentId":315,"scrollX":819,"scrollY":461},
{"id":330,"expanded":true,"name":"Room 7-3","order":314,"parentId":315,"scrollX":832,"scrollY":640},
{"id":331,"expanded":true,"name":"Room 7-4","order":315,"parentId":315,"scrollX":832,"scrollY":640},
{"id":332,"expanded":true,"name":"Entry","order":259,"parentId":193,"scrollX":819,"scrollY":461},
{"id":333,"expanded":true,"name":"Ticket Booth","order":260,"parentId":193,"scrollX":819,"scrollY":461},
{"id":334,"expanded":true,"name":"Checkpoint","order":261,"parentId":193,"scrollX":819,"scrollY":461},
{"id":335,"expanded":true,"name":"Left Stairs","order":262,"parentId":193,"scrollX":819,"scrollY":461},
{"id":336,"expanded":true,"name":"Right Stairs","order":264,"parentId":193,"scrollX":819,"scrollY":461},
{"id":337,"expanded":true,"name":"Guardroom","order":266,"parentId":193,"scrollX":819,"scrollY":461},
{"id":338,"expanded":true,"name":"Lockers","order":267,"parentId":193,"scrollX":811,"scrollY":461},
{"id":339,"expanded":true,"name":"Field","order":268,"parentId":193,"scrollX":1015,"scrollY":453},
{"id":340,"expanded":true,"name":"Jewel Vault 1","order":255,"parentId":181,"scrollX":819,"scrollY":461},
{"id":341,"expanded":true,"name":"Jewel Vault 2","order":256,"parentId":181,"scrollX":811,"scrollY":979},
{"id":342,"expanded":true,"name":"Left Seats","order":263,"parentId":335,"scrollX":819,"scrollY":461},
{"id":343,"expanded":true,"name":"Right Seats","order":265,"parentId":336,"scrollX":819,"scrollY":461},
{"id":344,"expanded":true,"name":"Entry","order":270,"parentId":194,"scrollX":819,"scrollY":461},
{"id":345,"expanded":true,"name":"Slut Bar","order":271,"parentId":194,"scrollX":811,"scrollY":476},
{"id":346,"expanded":true,"name":"Private Room 1","order":272,"parentId":345,"scrollX":819,"scrollY":461},
{"id":347,"expanded":true,"name":"Private Room 2","order":273,"parentId":345,"scrollX":819,"scrollY":448.5},
{"id":348,"expanded":true,"name":"Private Room 3","order":274,"parentId":345,"scrollX":819,"scrollY":461},
{"id":349,"expanded":true,"name":"Private Room 4","order":275,"parentId":345,"scrollX":478,"scrollY":448.5},
{"id":350,"expanded":true,"name":"Shandra's Office","order":277,"parentId":194,"scrollX":819,"scrollY":461},
{"id":351,"expanded":true,"name":"Guarded Room","order":276,"parentId":194,"scrollX":819,"scrollY":461},
{"id":352,"expanded":true,"name":"Gallery Windows 1","order":167,"parentId":271,"scrollX":819,"scrollY":461},
{"id":353,"expanded":true,"name":"Gallery Windows 2","order":168,"parentId":271,"scrollX":819,"scrollY":461},
{"id":354,"expanded":true,"name":"Kepiat's Diary","order":169,"parentId":271,"scrollX":819,"scrollY":461},
{"id":355,"expanded":true,"name":"Hall 1","order":170,"parentId":271,"scrollX":819,"scrollY":461},
{"id":356,"expanded":true,"name":"Hall 2","order":171,"parentId":271,"scrollX":819,"scrollY":461},
{"id":357,"expanded":true,"name":"Statue Doors","order":172,"parentId":271,"scrollX":819,"scrollY":461},
{"id":358,"expanded":true,"name":"Exhibition Hall","order":173,"parentId":357,"scrollX":811,"scrollY":781},
{"id":359,"expanded":true,"name":"Studio Hall","order":175,"parentId":357,"scrollX":819,"scrollY":461},
{"id":360,"expanded":true,"name":"Boss Hall","order":177,"parentId":357,"scrollX":819,"scrollY":461},
{"id":361,"expanded":true,"name":"Lilina Door","order":178,"parentId":360,"scrollX":819,"scrollY":461},
{"id":362,"expanded":true,"name":"Exhibition Room","order":174,"parentId":358,"scrollX":811,"scrollY":647},
{"id":363,"expanded":true,"name":"Kepiat's Studio","order":176,"parentId":359,"scrollX":811,"scrollY":617},
{"id":364,"expanded":true,"name":"Kepiat's Room","order":179,"parentId":360,"scrollX":811,"scrollY":621},
{"id":365,"expanded":true,"name":"Kepiat's Room (Open)","order":180,"parentId":364,"scrollX":811,"scrollY":581},
{"id":366,"expanded":true,"name":"Right Hall 1","order":440,"parentId":279,"scrollX":478,"scrollY":448.5},
{"id":367,"expanded":true,"name":"Treasure Room 2","order":442,"parentId":366,"scrollX":832,"scrollY":640},
{"id":368,"expanded":true,"name":"Right Hall 2","order":443,"parentId":279,"scrollX":478,"scrollY":448.5},
{"id":369,"expanded":true,"name":"Right Hall 3","order":444,"parentId":279,"scrollX":478,"scrollY":448.5},
{"id":370,"expanded":true,"name":"Left Puzzle Room","order":445,"parentId":279,"scrollX":338,"scrollY":448.5},
{"id":371,"expanded":true,"name":"Left Hall 1","order":448,"parentId":279,"scrollX":819,"scrollY":461},
{"id":372,"expanded":true,"name":"Treasure Room 1","order":446,"parentId":370,"scrollX":478,"scrollY":448.5},
{"id":373,"expanded":true,"name":"Convergence Hall","order":450,"parentId":279,"scrollX":819,"scrollY":461},
{"id":374,"expanded":true,"name":"Left Hall 2","order":449,"parentId":279,"scrollX":819,"scrollY":461},
{"id":375,"expanded":false,"name":"Last Puzzle Room","order":452,"parentId":279,"scrollX":811,"scrollY":787},
{"id":376,"expanded":true,"name":"Observation Room","order":453,"parentId":279,"scrollX":819,"scrollY":461},
{"id":377,"expanded":true,"name":"Bonus Puzzle Room","order":441,"parentId":366,"scrollX":478,"scrollY":448.5},
{"id":378,"expanded":true,"name":"Extra Room","order":447,"parentId":370,"scrollX":819,"scrollY":461},
{"id":379,"expanded":true,"name":"\"Throne\" Room","order":451,"parentId":373,"scrollX":819,"scrollY":461},
{"id":380,"expanded":true,"name":"Foyer","order":625,"parentId":245,"scrollX":1334,"scrollY":795},
{"id":381,"expanded":true,"name":"Library","order":630,"parentId":245,"scrollX":811,"scrollY":787},
{"id":382,"expanded":true,"name":"Dining Room","order":631,"parentId":245,"scrollX":819,"scrollY":461},
{"id":383,"expanded":true,"name":"Kitchen","order":632,"parentId":245,"scrollX":819,"scrollY":461},
{"id":384,"expanded":true,"name":"Study","order":633,"parentId":245,"scrollX":819,"scrollY":461},
{"id":385,"expanded":true,"name":"Master Living Room","order":646,"parentId":632,"scrollX":819,"scrollY":453},
{"id":386,"expanded":true,"name":"Master Bedroom","order":647,"parentId":385,"scrollX":819,"scrollY":461},
{"id":387,"expanded":true,"name":"Throne Room (FE4)","order":889,"parentId":779,"scrollX":819,"scrollY":461},
{"id":388,"expanded":true,"name":"Item Shop","order":542,"parentId":444,"scrollX":832,"scrollY":640},
{"id":389,"expanded":true,"name":"Forestkin Village (After)","order":575,"parentId":590,"scrollX":819,"scrollY":461},
{"id":390,"expanded":false,"name":"Entry 1","order":591,"parentId":241,"scrollX":819,"scrollY":461},
{"id":391,"expanded":false,"name":"Entry 2","order":592,"parentId":241,"scrollX":819,"scrollY":461},
{"id":392,"expanded":false,"name":"Stairs Down","order":593,"parentId":241,"scrollX":819,"scrollY":461},
{"id":393,"expanded":false,"name":"Ingredient Shipment","order":594,"parentId":241,"scrollX":819,"scrollY":461},
{"id":394,"expanded":true,"name":"Processing Facility","order":595,"parentId":241,"scrollX":811,"scrollY":462},
{"id":395,"expanded":false,"name":"Hall 1","order":599,"parentId":241,"scrollX":819,"scrollY":461},
{"id":396,"expanded":false,"name":"Hall 2","order":600,"parentId":241,"scrollX":819,"scrollY":461},
{"id":397,"expanded":false,"name":"Hall 3","order":601,"parentId":241,"scrollX":1404,"scrollY":790.2857142857142},
{"id":398,"expanded":false,"name":"Hall 4","order":602,"parentId":241,"scrollX":819,"scrollY":461},
{"id":399,"expanded":false,"name":"Hall 5","order":603,"parentId":241,"scrollX":832,"scrollY":640},
{"id":400,"expanded":true,"name":"Hall 6","order":604,"parentId":241,"scrollX":819,"scrollY":461},
{"id":401,"expanded":true,"name":"Vemix Door 1","order":596,"parentId":394,"scrollX":819,"scrollY":461},
{"id":402,"expanded":false,"name":"Vemix Door 1 (Open)","order":597,"parentId":401,"scrollX":819,"scrollY":461},
{"id":403,"expanded":false,"name":"Testing Chamber 01","order":598,"parentId":401,"scrollX":338,"scrollY":448.5},
{"id":404,"expanded":true,"name":"Vemix Door 2","order":605,"parentId":400,"scrollX":832,"scrollY":640},
{"id":405,"expanded":false,"name":"Vemix Door 2 (Open)","order":606,"parentId":404,"scrollX":819,"scrollY":461},
{"id":406,"expanded":false,"name":"Testing Chamber 02","order":607,"parentId":404,"scrollX":819,"scrollY":461},
{"id":407,"expanded":true,"name":"Vemix Door 3","order":608,"parentId":400,"scrollX":819,"scrollY":461},
{"id":408,"expanded":false,"name":"Vemix Door 3 (Open)","order":609,"parentId":407,"scrollX":478,"scrollY":448.5},
{"id":409,"expanded":false,"name":"Testing Chamber 03","order":610,"parentId":407,"scrollX":478,"scrollY":448.5},
{"id":410,"expanded":true,"name":"Aquatic Research","order":613,"parentId":241,"scrollX":819,"scrollY":453},
{"id":411,"expanded":false,"name":"Submarine Dock","order":614,"parentId":410,"scrollX":819,"scrollY":461},
{"id":412,"expanded":false,"name":"Guarded Hall","order":615,"parentId":241,"scrollX":819,"scrollY":461},
{"id":413,"expanded":false,"name":"DEMO Forest","order":617,"parentId":242,"scrollX":819,"scrollY":461},
{"id":414,"expanded":false,"name":"DEMO Market","order":618,"parentId":242,"scrollX":817,"scrollY":455.5},
{"id":415,"expanded":false,"name":"DEMO Plains","order":619,"parentId":242,"scrollX":819,"scrollY":461},
{"id":416,"expanded":false,"name":"DEMO Woodrot","order":620,"parentId":242,"scrollX":819,"scrollY":461},
{"id":417,"expanded":false,"name":"DEMO Tower","order":621,"parentId":242,"scrollX":819,"scrollY":461},
{"id":418,"expanded":false,"name":"DEMO Mountains","order":622,"parentId":242,"scrollX":819,"scrollY":461},
{"id":419,"expanded":true,"name":"Lair of the Puppetmaster M","order":51,"parentId":723,"scrollX":811,"scrollY":461},
{"id":420,"expanded":false,"name":"Sandbox Castle Copy Arena","order":21,"parentId":1,"scrollX":819,"scrollY":461},
{"id":421,"expanded":true,"name":"Witch's Abode","order":422,"parentId":221,"scrollX":819,"scrollY":453},
{"id":422,"expanded":true,"name":"Big Top Entrance","order":351,"parentId":272,"scrollX":819,"scrollY":461},
{"id":423,"expanded":true,"name":"Hessa's Building","order":357,"parentId":272,"scrollX":819,"scrollY":461},
{"id":424,"expanded":true,"name":"Pollur's Building","order":358,"parentId":272,"scrollX":819,"scrollY":461},
{"id":425,"expanded":true,"name":"Prime Minister's Office","order":60,"parentId":19,"scrollX":819,"scrollY":461},
{"id":426,"expanded":true,"name":"Circus Entrance (Closed)","order":348,"parentId":159,"scrollX":819,"scrollY":461},
{"id":427,"expanded":true,"name":"Side Room","order":353,"parentId":428,"scrollX":817,"scrollY":455.5},
{"id":428,"expanded":true,"name":"Big Top Entrance (Alt)","order":352,"parentId":422,"scrollX":819,"scrollY":461},
{"id":429,"expanded":true,"name":"Side Room 2","order":354,"parentId":428,"scrollX":819,"scrollY":461},
{"id":430,"expanded":true,"name":"Pollur/Hessa's Room","order":355,"parentId":428,"scrollX":819,"scrollY":461},
{"id":431,"expanded":true,"name":"Big Top","order":356,"parentId":422,"scrollX":811,"scrollY":795},
{"id":432,"expanded":true,"name":"Throne Room (Intro)","order":58,"parentId":18,"scrollX":819,"scrollY":461},
{"id":433,"expanded":true,"name":"Mt. Pleasant Left 1","order":533,"parentId":239,"scrollX":819,"scrollY":461},
{"id":434,"expanded":true,"name":"Mt. Pleasant Left 2","order":534,"parentId":239,"scrollX":832,"scrollY":640},
{"id":435,"expanded":true,"name":"Mt. Pleasant Left 3","order":535,"parentId":239,"scrollX":819,"scrollY":461},
{"id":436,"expanded":true,"name":"Tabnath Left 1","order":491,"parentId":237,"scrollX":817,"scrollY":455.5},
{"id":437,"expanded":true,"name":"Tabnath Left 2","order":495,"parentId":237,"scrollX":832,"scrollY":640},
{"id":438,"expanded":true,"name":"Tabnath Left 3","order":499,"parentId":237,"scrollX":819,"scrollY":461},
{"id":439,"expanded":true,"name":"Tabnath Left 4","order":503,"parentId":237,"scrollX":819,"scrollY":461},
{"id":440,"expanded":true,"name":"Tabnath Left 5","order":505,"parentId":237,"scrollX":819,"scrollY":461},
{"id":441,"expanded":true,"name":"Tabnath Left 6","order":514,"parentId":237,"scrollX":819,"scrollY":461},
{"id":442,"expanded":true,"name":"Mead Hall","order":515,"parentId":441,"scrollX":811,"scrollY":461},
{"id":443,"expanded":true,"name":"Mt. Pleasant Right 1","order":540,"parentId":239,"scrollX":478,"scrollY":448.5},
{"id":444,"expanded":true,"name":"Mt. Pleasant Right 2","order":541,"parentId":239,"scrollX":832,"scrollY":640},
{"id":445,"expanded":true,"name":"Mt. Pleasant Right 3","order":543,"parentId":239,"scrollX":819,"scrollY":461},
{"id":446,"expanded":true,"name":"Mt. Pleasant Right 4","order":545,"parentId":239,"scrollX":811,"scrollY":461},
{"id":447,"expanded":true,"name":"Farmland","order":556,"parentId":239,"scrollX":819,"scrollY":461},
{"id":448,"expanded":true,"name":"Farmland Entrance","order":557,"parentId":447,"scrollX":819,"scrollY":461},
{"id":449,"expanded":true,"name":"Southwest Woodrot","order":569,"parentId":239,"scrollX":819,"scrollY":461},
{"id":450,"expanded":true,"name":"Woodrot Path 1","order":570,"parentId":449,"scrollX":832,"scrollY":640},
{"id":451,"expanded":true,"name":"City View","order":682,"parentId":250,"scrollX":832,"scrollY":640},
{"id":452,"expanded":true,"name":"Tabnath Right 1","order":518,"parentId":237,"scrollX":819,"scrollY":461},
{"id":453,"expanded":true,"name":"Armor Shop","order":492,"parentId":436,"scrollX":819,"scrollY":461},
{"id":454,"expanded":true,"name":"Weapon Shop","order":496,"parentId":437,"scrollX":832,"scrollY":640},
{"id":455,"expanded":true,"name":"Egg Market","order":500,"parentId":438,"scrollX":819,"scrollY":461},
{"id":456,"expanded":true,"name":"Tabnath Left 5 (After)","order":506,"parentId":440,"scrollX":819,"scrollY":461},
{"id":457,"expanded":true,"name":"Lyra's Manor","order":70,"parentId":22,"scrollX":819,"scrollY":461},
{"id":458,"expanded":true,"name":"Bridge 1","order":683,"parentId":250,"scrollX":832,"scrollY":640},
{"id":459,"expanded":true,"name":"Descending Bridge","order":692,"parentId":250,"scrollX":819,"scrollY":461},
{"id":460,"expanded":true,"name":"Tower Entry","order":684,"parentId":458,"scrollX":832,"scrollY":640},
{"id":461,"expanded":true,"name":"Infinite Plaza","order":693,"parentId":250,"scrollX":811,"scrollY":787},
{"id":462,"expanded":true,"name":"Infinite Plaza (Solved)","order":694,"parentId":461,"scrollX":821,"scrollY":787},
{"id":463,"expanded":true,"name":"Occupied Tabnath Entrance","order":490,"parentId":238,"scrollX":832,"scrollY":640},
{"id":464,"expanded":true,"name":"Arena Entry","order":519,"parentId":452,"scrollX":819,"scrollY":461},
{"id":465,"expanded":true,"name":"Cheat Room","order":61,"parentId":19,"scrollX":819,"scrollY":461},
{"id":466,"expanded":true,"name":"Passenger Car 1","order":650,"parentId":247,"scrollX":819,"scrollY":461},
{"id":467,"expanded":true,"name":"Passenger Car 2","order":651,"parentId":247,"scrollX":819,"scrollY":461},
{"id":468,"expanded":true,"name":"Dining Car","order":652,"parentId":247,"scrollX":819,"scrollY":461},
{"id":469,"expanded":true,"name":"Kitchen Car","order":653,"parentId":247,"scrollX":819,"scrollY":461},
{"id":470,"expanded":true,"name":"Alchemy Shop Outside","order":507,"parentId":456,"scrollX":832,"scrollY":640},
{"id":471,"expanded":true,"name":"Orcish Alchemy Shop","order":509,"parentId":456,"scrollX":819,"scrollY":461},
{"id":472,"expanded":true,"name":"Maester's Manor","order":536,"parentId":435,"scrollX":819,"scrollY":461},
{"id":473,"expanded":true,"name":"Maester's Manor Open","order":537,"parentId":472,"scrollX":819,"scrollY":461},
{"id":474,"expanded":true,"name":"Maester's Balcony","order":539,"parentId":435,"scrollX":819,"scrollY":461},
{"id":475,"expanded":true,"name":"Farmland NW","order":558,"parentId":447,"scrollX":811,"scrollY":779},
{"id":476,"expanded":true,"name":"Farmland N","order":559,"parentId":447,"scrollX":811,"scrollY":619},
{"id":477,"expanded":true,"name":"Farmland NE","order":560,"parentId":447,"scrollX":811,"scrollY":713},
{"id":478,"expanded":true,"name":"Farmland W","order":561,"parentId":447,"scrollX":821,"scrollY":593},
{"id":479,"expanded":true,"name":"Farmland Center","order":562,"parentId":447,"scrollX":811,"scrollY":779},
{"id":480,"expanded":true,"name":"Farmland E","order":563,"parentId":447,"scrollX":811,"scrollY":461},
{"id":481,"expanded":true,"name":"Farmland SW","order":564,"parentId":447,"scrollX":821,"scrollY":653},
{"id":482,"expanded":true,"name":"Farmland S","order":565,"parentId":447,"scrollX":821,"scrollY":655},
{"id":483,"expanded":true,"name":"Farmland SE","order":567,"parentId":447,"scrollX":811,"scrollY":625},
{"id":484,"expanded":true,"name":"Ocean Overlook","order":566,"parentId":482,"scrollX":811,"scrollY":461},
{"id":485,"expanded":true,"name":"Luxatep Road 2","order":470,"parentId":235,"scrollX":819,"scrollY":461},
{"id":486,"expanded":true,"name":"Luxatep Road 3","order":472,"parentId":235,"scrollX":819,"scrollY":461},
{"id":487,"expanded":true,"name":"Luxatep Road 4","order":473,"parentId":235,"scrollX":832,"scrollY":640},
{"id":488,"expanded":true,"name":"Luxatep Road 5 (Fast Travel)","order":474,"parentId":235,"scrollX":819,"scrollY":461},
{"id":489,"expanded":true,"name":"Luxatep Road 6","order":475,"parentId":235,"scrollX":819,"scrollY":461},
{"id":490,"expanded":true,"name":"Luxatep Road 7 (Tomb Entry)","order":478,"parentId":235,"scrollX":819,"scrollY":461},
{"id":491,"expanded":true,"name":"Luxatep Road 8","order":479,"parentId":235,"scrollX":982.8,"scrollY":553.1999999999999},
{"id":492,"expanded":true,"name":"Stairwell","order":785,"parentId":257,"scrollX":819,"scrollY":461},
{"id":493,"expanded":true,"name":"Hargrave Courtyard","order":793,"parentId":257,"scrollX":811,"scrollY":1795},
{"id":494,"expanded":true,"name":"Hargrave Castle","order":788,"parentId":257,"scrollX":819,"scrollY":461},
{"id":495,"expanded":true,"name":"Stairwell Up","order":786,"parentId":492,"scrollX":819,"scrollY":461},
{"id":496,"expanded":true,"name":"Upper Courtyard","order":791,"parentId":257,"scrollX":819,"scrollY":461},
{"id":497,"expanded":true,"name":"Chateau Dock","order":366,"parentId":165,"scrollX":819,"scrollY":461},
{"id":498,"expanded":true,"name":"Occupied Armor Shop","order":494,"parentId":524,"scrollX":832,"scrollY":640},
{"id":499,"expanded":true,"name":"Hargrave Castle (Open)","order":789,"parentId":494,"scrollX":832,"scrollY":640},
{"id":500,"expanded":true,"name":"Hall of Souls","order":790,"parentId":494,"scrollX":832,"scrollY":640},
{"id":501,"expanded":true,"name":"Hargrave's Bedchamber","order":787,"parentId":492,"scrollX":819,"scrollY":461},
{"id":502,"expanded":true,"name":"Puppet Workshop","order":461,"parentId":232,"scrollX":819,"scrollY":461},
{"id":503,"expanded":true,"name":"World Map","order":22,"parentId":1,"scrollX":811,"scrollY":453},
{"id":504,"expanded":true,"name":"Bridge 2","order":696,"parentId":250,"scrollX":819,"scrollY":461},
{"id":505,"expanded":true,"name":"Big Door","order":697,"parentId":250,"scrollX":819,"scrollY":461},
{"id":506,"expanded":true,"name":"Descending Bridge 2","order":699,"parentId":250,"scrollX":819,"scrollY":461},
{"id":507,"expanded":true,"name":"Looping Bridge","order":700,"parentId":250,"scrollX":811,"scrollY":461},
{"id":508,"expanded":true,"name":"Large Tower / Stairs","order":701,"parentId":250,"scrollX":819,"scrollY":461},
{"id":509,"expanded":true,"name":"Large Tower / Stairs (Open)","order":702,"parentId":508,"scrollX":819,"scrollY":461},
{"id":510,"expanded":true,"name":"Descending Bridge 3","order":707,"parentId":250,"scrollX":819,"scrollY":461},
{"id":511,"expanded":true,"name":"Bridge Fork","order":708,"parentId":250,"scrollX":478,"scrollY":448.5},
{"id":512,"expanded":true,"name":"Bridge 3","order":709,"parentId":250,"scrollX":819,"scrollY":461},
{"id":513,"expanded":true,"name":"Bridge Fork?","order":710,"parentId":250,"scrollX":338,"scrollY":448.5},
{"id":514,"expanded":true,"name":"Fake Throne Room (Intro)","order":712,"parentId":250,"scrollX":819,"scrollY":461},
{"id":515,"expanded":true,"name":"Fake Throne Room","order":713,"parentId":514,"scrollX":478,"scrollY":448.5},
{"id":516,"expanded":true,"name":"Fake Stairwell","order":714,"parentId":514,"scrollX":819,"scrollY":461},
{"id":517,"expanded":true,"name":"Fake Gianna Castle","order":716,"parentId":514,"scrollX":819,"scrollY":461},
{"id":518,"expanded":true,"name":"Bridge Fork? (After)","order":711,"parentId":513,"scrollX":478,"scrollY":448.5},
{"id":519,"expanded":true,"name":"Descent into Mountains","order":717,"parentId":250,"scrollX":811,"scrollY":461},
{"id":520,"expanded":true,"name":"Descent End","order":718,"parentId":250,"scrollX":819,"scrollY":461},
{"id":521,"expanded":true,"name":"Mountain Overlook","order":720,"parentId":250,"scrollX":819,"scrollY":461},
{"id":522,"expanded":true,"name":"Fake Stairwell (After)","order":715,"parentId":516,"scrollX":832,"scrollY":640},
{"id":523,"expanded":true,"name":"Arena","order":523,"parentId":535,"scrollX":811,"scrollY":453},
{"id":524,"expanded":true,"name":"Occupied Tabnath Left 1","order":493,"parentId":436,"scrollX":819,"scrollY":461},
{"id":525,"expanded":true,"name":"Occupied Tabnath Left 2","order":497,"parentId":437,"scrollX":819,"scrollY":461},
{"id":526,"expanded":true,"name":"Occupied Weapon Shop","order":498,"parentId":525,"scrollX":819,"scrollY":461},
{"id":527,"expanded":true,"name":"Occupied Tabnath Left 3","order":501,"parentId":438,"scrollX":819,"scrollY":453},
{"id":528,"expanded":true,"name":"Occupied Egg Market","order":502,"parentId":527,"scrollX":478,"scrollY":448.5},
{"id":529,"expanded":true,"name":"Occupied Tabnath Left 4","order":504,"parentId":439,"scrollX":819,"scrollY":461},
{"id":530,"expanded":true,"name":"Occupied Tabnath Left 5","order":510,"parentId":456,"scrollX":819,"scrollY":461},
{"id":531,"expanded":true,"name":"Occupied Alchemy Shop Outside","order":511,"parentId":530,"scrollX":819,"scrollY":461},
{"id":532,"expanded":true,"name":"Occupied Alchemy Shop","order":513,"parentId":530,"scrollX":819,"scrollY":461},
{"id":533,"expanded":true,"name":"Occupied Tabnath Left 6","order":516,"parentId":441,"scrollX":819,"scrollY":461},
{"id":534,"expanded":true,"name":"Occupied Mead Hall","order":517,"parentId":533,"scrollX":811,"scrollY":461},
{"id":535,"expanded":true,"name":"Occupied Tabnath Right 1","order":520,"parentId":452,"scrollX":478,"scrollY":448.5},
{"id":536,"expanded":true,"name":"Occupied Arena Entry","order":521,"parentId":535,"scrollX":819,"scrollY":461},
{"id":537,"expanded":true,"name":"Occupied Arena","order":522,"parentId":535,"scrollX":869,"scrollY":795},
{"id":538,"expanded":true,"name":"Tabnath Right 2","order":524,"parentId":237,"scrollX":819,"scrollY":461},
{"id":539,"expanded":true,"name":"Arena Cells","order":525,"parentId":538,"scrollX":819,"scrollY":461},
{"id":540,"expanded":true,"name":"Cattle Stable","order":527,"parentId":538,"scrollX":832,"scrollY":640},
{"id":541,"expanded":true,"name":"Occupied Tabnath Right 2","order":528,"parentId":538,"scrollX":819,"scrollY":461},
{"id":542,"expanded":true,"name":"Occupied Arena Cells","order":529,"parentId":541,"scrollX":819,"scrollY":461},
{"id":543,"expanded":true,"name":"Occupied Cattle Stable","order":530,"parentId":541,"scrollX":819,"scrollY":461},
{"id":544,"expanded":true,"name":"Occupied West Tabnath","order":368,"parentId":166,"scrollX":4085,"scrollY":2297},
{"id":545,"expanded":true,"name":"Arena Cells (After)","order":526,"parentId":539,"scrollX":819,"scrollY":461},
{"id":546,"expanded":false,"name":"Room 6-1 (After)","order":309,"parentId":314,"scrollX":819,"scrollY":461},
{"id":547,"expanded":true,"name":"Verona's","order":464,"parentId":233,"scrollX":819,"scrollY":461},
{"id":548,"expanded":true,"name":"Maester's Dungeon","order":538,"parentId":472,"scrollX":478,"scrollY":448.5},
{"id":549,"expanded":true,"name":"Kasmut's Tent","order":476,"parentId":489,"scrollX":819,"scrollY":461},
{"id":550,"expanded":true,"name":"Annie's","order":457,"parentId":230,"scrollX":819,"scrollY":461},
{"id":551,"expanded":true,"name":"Miss Diana's","order":458,"parentId":230,"scrollX":819,"scrollY":461},
{"id":552,"expanded":false,"name":"Train Platform (Empty)","order":681,"parentId":252,"scrollX":478,"scrollY":448.5},
{"id":553,"expanded":true,"name":"Woodrot Path 2","order":571,"parentId":449,"scrollX":819,"scrollY":461},
{"id":554,"expanded":true,"name":"General Store","order":462,"parentId":232,"scrollX":819,"scrollY":461},
{"id":555,"expanded":true,"name":"Entry","order":735,"parentId":255,"scrollX":819,"scrollY":461},
{"id":556,"expanded":true,"name":"Main Hall","order":736,"parentId":255,"scrollX":811,"scrollY":577},
{"id":557,"expanded":true,"name":"Side Hall Left","order":738,"parentId":255,"scrollX":819,"scrollY":461},
{"id":558,"expanded":true,"name":"Side Hall Right","order":741,"parentId":255,"scrollX":819,"scrollY":461},
{"id":559,"expanded":true,"name":"Hidden Room 4","order":737,"parentId":556,"scrollX":819,"scrollY":461},
{"id":560,"expanded":true,"name":"Monument Hall","order":739,"parentId":557,"scrollX":1260,"scrollY":697},
{"id":561,"expanded":true,"name":"Hidden Room 1","order":740,"parentId":560,"scrollX":819,"scrollY":461},
{"id":562,"expanded":true,"name":"Hidden Room 5","order":477,"parentId":489,"scrollX":819,"scrollY":461},
{"id":563,"expanded":true,"name":"Maze 1","order":742,"parentId":558,"scrollX":819,"scrollY":461},
{"id":564,"expanded":true,"name":"Maze 2","order":743,"parentId":558,"scrollX":819,"scrollY":461},
{"id":565,"expanded":true,"name":"Maze 3","order":744,"parentId":558,"scrollX":819,"scrollY":461},
{"id":566,"expanded":true,"name":"Maze 4","order":745,"parentId":558,"scrollX":819,"scrollY":461},
{"id":567,"expanded":true,"name":"Maze 5","order":746,"parentId":558,"scrollX":832,"scrollY":640},
{"id":568,"expanded":true,"name":"Maze 6","order":747,"parentId":558,"scrollX":832,"scrollY":640},
{"id":569,"expanded":true,"name":"Maze 7","order":748,"parentId":558,"scrollX":832,"scrollY":640},
{"id":570,"expanded":true,"name":"Maze 8","order":749,"parentId":558,"scrollX":819,"scrollY":461},
{"id":571,"expanded":true,"name":"Maze 9","order":750,"parentId":558,"scrollX":832,"scrollY":640},
{"id":572,"expanded":true,"name":"Maze 10","order":751,"parentId":558,"scrollX":819,"scrollY":461},
{"id":573,"expanded":true,"name":"Maze 11","order":753,"parentId":558,"scrollX":832,"scrollY":640},
{"id":574,"expanded":true,"name":"Maze 12","order":754,"parentId":558,"scrollX":832,"scrollY":640},
{"id":575,"expanded":true,"name":"Maze 13","order":755,"parentId":558,"scrollX":832,"scrollY":640},
{"id":576,"expanded":true,"name":"Maze 14","order":756,"parentId":558,"scrollX":819,"scrollY":461},
{"id":577,"expanded":true,"name":"Maze 15","order":758,"parentId":558,"scrollX":819,"scrollY":461},
{"id":578,"expanded":true,"name":"Maze 16","order":759,"parentId":558,"scrollX":819,"scrollY":461},
{"id":579,"expanded":true,"name":"Maze 17","order":760,"parentId":558,"scrollX":819,"scrollY":461},
{"id":580,"expanded":true,"name":"Maze 14 (Open)","order":757,"parentId":576,"scrollX":819,"scrollY":461},
{"id":581,"expanded":true,"name":"Hidden Room 3","order":752,"parentId":572,"scrollX":832,"scrollY":640},
{"id":582,"expanded":true,"name":"Sarcophagus Hall 1","order":761,"parentId":255,"scrollX":819,"scrollY":461},
{"id":583,"expanded":true,"name":"Hidden Room 2","order":762,"parentId":582,"scrollX":819,"scrollY":461},
{"id":584,"expanded":true,"name":"Sarcophagus Hall 2","order":763,"parentId":255,"scrollX":819,"scrollY":461},
{"id":585,"expanded":true,"name":"Sarcophagus Hall 3","order":764,"parentId":255,"scrollX":819,"scrollY":461},
{"id":586,"expanded":true,"name":"East Tabnath (No Station)","order":371,"parentId":167,"scrollX":2433,"scrollY":1737},
{"id":587,"expanded":true,"name":"Hall 7","order":611,"parentId":400,"scrollX":478,"scrollY":448.5},
{"id":588,"expanded":true,"name":"Subject Storage","order":612,"parentId":587,"scrollX":819,"scrollY":461},
{"id":589,"expanded":true,"name":"Woodrot Path 3","order":573,"parentId":449,"scrollX":819,"scrollY":461},
{"id":590,"expanded":true,"name":"Forestkin Village","order":574,"parentId":449,"scrollX":819,"scrollY":461},
{"id":591,"expanded":false,"name":"Windmill 1","order":546,"parentId":446,"scrollX":819,"scrollY":461},
{"id":592,"expanded":false,"name":"Windmill 2","order":547,"parentId":446,"scrollX":819,"scrollY":461},
{"id":593,"expanded":false,"name":"Windmill 3","order":548,"parentId":446,"scrollX":819,"scrollY":461},
{"id":594,"expanded":false,"name":"Windmill 4","order":549,"parentId":446,"scrollX":832,"scrollY":640},
{"id":595,"expanded":false,"name":"Windmill 5","order":550,"parentId":446,"scrollX":832,"scrollY":640},
{"id":596,"expanded":true,"name":"Windmill 6","order":551,"parentId":446,"scrollX":819,"scrollY":461},
{"id":597,"expanded":true,"name":"Windmill 7","order":553,"parentId":446,"scrollX":832,"scrollY":640},
{"id":598,"expanded":false,"name":"Windmill Top","order":555,"parentId":446,"scrollX":819,"scrollY":461},
{"id":599,"expanded":true,"name":"Windmill Balcony","order":552,"parentId":596,"scrollX":819,"scrollY":461},
{"id":600,"expanded":true,"name":"Greenhouse","order":568,"parentId":483,"scrollX":811,"scrollY":453},
{"id":601,"expanded":true,"name":"Ascent","order":372,"parentId":167,"scrollX":811,"scrollY":787},
{"id":602,"expanded":true,"name":"Warp House","order":76,"parentId":259,"scrollX":819,"scrollY":461},
{"id":603,"expanded":false,"name":"Warp Room","order":554,"parentId":597,"scrollX":832,"scrollY":640},
{"id":604,"expanded":true,"name":"Beach (Train Platform)","order":469,"parentId":605,"scrollX":832,"scrollY":640},
{"id":605,"expanded":true,"name":"Beach","order":468,"parentId":236,"scrollX":832,"scrollY":640},
{"id":606,"expanded":true,"name":"Southern Forest 7 (Train Platform)","order":204,"parentId":106,"scrollX":832,"scrollY":640},
{"id":607,"expanded":true,"name":"Uphill Path 3 (Train Platform)","order":429,"parentId":227,"scrollX":832,"scrollY":640},
{"id":608,"expanded":true,"name":"Tower Forest 1 (Train Platform)","order":212,"parentId":115,"scrollX":832,"scrollY":640},
{"id":609,"expanded":true,"name":"Woodrot Forest 34 (Train Platform)","order":416,"parentId":216,"scrollX":819,"scrollY":461},
{"id":610,"expanded":true,"name":"Alchemy Shop Outside (Train Platform)","order":508,"parentId":470,"scrollX":832,"scrollY":640},
{"id":611,"expanded":true,"name":"Occupied Alchemy Shop Outside (Train Platform)","order":512,"parentId":531,"scrollX":819,"scrollY":461},
{"id":612,"expanded":true,"name":"Sea Market Road 2 (Train Platform)","order":122,"parentId":41,"scrollX":832,"scrollY":640},
{"id":613,"expanded":true,"name":"Middle Tabnath 2 (Train Platform)","order":362,"parentId":162,"scrollX":817,"scrollY":455.5},
{"id":614,"expanded":true,"name":"Foyer","order":654,"parentId":247,"scrollX":2445,"scrollY":453},
{"id":615,"expanded":true,"name":"Library Car","order":661,"parentId":247,"scrollX":811,"scrollY":1040},
{"id":616,"expanded":true,"name":"West Plains 1 (Train Platform)","order":132,"parentId":51,"scrollX":819,"scrollY":461},
{"id":617,"expanded":true,"name":"Bar Car","order":659,"parentId":247,"scrollX":819,"scrollY":461},
{"id":618,"expanded":true,"name":"First-Class Car","order":660,"parentId":247,"scrollX":478,"scrollY":448.5},
{"id":619,"expanded":true,"name":"Garuda's Vision","order":662,"parentId":615,"scrollX":819,"scrollY":461},
{"id":620,"expanded":true,"name":"Gluttony's Vision","order":663,"parentId":615,"scrollX":478,"scrollY":448.5},
{"id":621,"expanded":true,"name":"Yousheng Ma's Vision","order":664,"parentId":615,"scrollX":819,"scrollY":461},
{"id":622,"expanded":true,"name":"Greta Markos' Vision","order":665,"parentId":615,"scrollX":819,"scrollY":461},
{"id":623,"expanded":true,"name":"Samona Shah's Vision","order":666,"parentId":615,"scrollX":819,"scrollY":461},
{"id":624,"expanded":true,"name":"Unega the Wise's Vision","order":667,"parentId":615,"scrollX":819,"scrollY":461},
{"id":625,"expanded":true,"name":"Saint Urania's Vision","order":668,"parentId":615,"scrollX":819,"scrollY":461},
{"id":626,"expanded":true,"name":"Earth-Fang Vemix's Vision","order":669,"parentId":615,"scrollX":819,"scrollY":461},
{"id":627,"expanded":true,"name":"Short Hall 1","order":626,"parentId":380,"scrollX":819,"scrollY":461},
{"id":628,"expanded":true,"name":"Casino Car","order":674,"parentId":247,"scrollX":819,"scrollY":461},
{"id":629,"expanded":true,"name":"Front Car","order":675,"parentId":247,"scrollX":819,"scrollY":461},
{"id":630,"expanded":true,"name":"Library Car (Open)","order":670,"parentId":615,"scrollX":811,"scrollY":1040},
{"id":631,"expanded":true,"name":"Conductor Car","order":676,"parentId":247,"scrollX":819,"scrollY":461},
{"id":632,"expanded":true,"name":"Foyer Overlook","order":634,"parentId":245,"scrollX":1637,"scrollY":454},
{"id":633,"expanded":true,"name":"Descent End (After)","order":719,"parentId":520,"scrollX":819,"scrollY":461},
{"id":634,"expanded":true,"name":"Bridge 4","order":721,"parentId":250,"scrollX":819,"scrollY":461},
{"id":635,"expanded":true,"name":"Bridge 5","order":722,"parentId":250,"scrollX":819,"scrollY":461},
{"id":636,"expanded":true,"name":"Vista Bench","order":723,"parentId":250,"scrollX":832,"scrollY":640},
{"id":637,"expanded":true,"name":"Big Door (Open)","order":698,"parentId":505,"scrollX":819,"scrollY":461},
{"id":638,"expanded":true,"name":"West Tower Entry","order":83,"parentId":849,"scrollX":819,"scrollY":461},
{"id":639,"expanded":true,"name":"Tower Foyer","order":685,"parentId":458,"scrollX":832,"scrollY":640},
{"id":640,"expanded":false,"name":"Tower Study","order":686,"parentId":458,"scrollX":338,"scrollY":448.5},
{"id":641,"expanded":true,"name":"Tower Bedroom","order":687,"parentId":458,"scrollX":832,"scrollY":640},
{"id":642,"expanded":true,"name":"Strange Pathway","order":724,"parentId":250,"scrollX":819,"scrollY":461},
{"id":643,"expanded":false,"name":"Mirror Bedroom","order":688,"parentId":641,"scrollX":819,"scrollY":461},
{"id":644,"expanded":true,"name":"Mirror Foyer","order":689,"parentId":641,"scrollX":478,"scrollY":448.5},
{"id":645,"expanded":false,"name":"Mirror Study","order":690,"parentId":641,"scrollX":819,"scrollY":461},
{"id":646,"expanded":true,"name":"Hidden Plaza","order":691,"parentId":458,"scrollX":819,"scrollY":461},
{"id":647,"expanded":true,"name":"Tinker's Car","order":655,"parentId":614,"scrollX":819,"scrollY":461},
{"id":648,"expanded":true,"name":"Spa","order":656,"parentId":614,"scrollX":819,"scrollY":461},
{"id":649,"expanded":true,"name":"Gallery Car","order":657,"parentId":614,"scrollX":817,"scrollY":455.5},
{"id":650,"expanded":true,"name":"Scribe's Car","order":658,"parentId":614,"scrollX":819,"scrollY":461},
{"id":651,"expanded":true,"name":"Tea Garden","order":627,"parentId":627,"scrollX":819,"scrollY":461},
{"id":652,"expanded":true,"name":"Short Hall 2","order":635,"parentId":632,"scrollX":819,"scrollY":461},
{"id":653,"expanded":true,"name":"Punishment Room","order":636,"parentId":652,"scrollX":819,"scrollY":461},
{"id":654,"expanded":true,"name":"Mountainview Balcony","order":637,"parentId":652,"scrollX":819,"scrollY":461},
{"id":655,"expanded":true,"name":"Gallery","order":638,"parentId":632,"scrollX":819,"scrollY":461},
{"id":656,"expanded":true,"name":"Long Hall","order":639,"parentId":632,"scrollX":819,"scrollY":448.5},
{"id":657,"expanded":true,"name":"Greenhouse","order":642,"parentId":656,"scrollX":478,"scrollY":448.5},
{"id":658,"expanded":true,"name":"Second Guest Bedroom","order":640,"parentId":656,"scrollX":819,"scrollY":461},
{"id":659,"expanded":true,"name":"First Guest Bedroom","order":641,"parentId":656,"scrollX":819,"scrollY":461},
{"id":660,"expanded":true,"name":"Sitting Room","order":643,"parentId":656,"scrollX":832,"scrollY":640},
{"id":661,"expanded":true,"name":"West Stairs","order":644,"parentId":632,"scrollX":819,"scrollY":461},
{"id":662,"expanded":true,"name":"East Stairs","order":645,"parentId":632,"scrollX":478,"scrollY":448.5},
{"id":663,"expanded":true,"name":"Gianna West","order":77,"parentId":22,"scrollX":819,"scrollY":461},
{"id":664,"expanded":true,"name":"Big Tower Entry","order":703,"parentId":509,"scrollX":819,"scrollY":461},
{"id":665,"expanded":true,"name":"Big Tower Entry (After)","order":704,"parentId":664,"scrollX":478,"scrollY":448.5},
{"id":666,"expanded":true,"name":"Big Tower Stairs","order":705,"parentId":509,"scrollX":819,"scrollY":461},
{"id":667,"expanded":true,"name":"Ballroom","order":706,"parentId":509,"scrollX":819,"scrollY":461},
{"id":668,"expanded":true,"name":"Under-Stairs Pedestal Room (OLD)","order":23,"parentId":1,"scrollX":819,"scrollY":461},
{"id":669,"expanded":true,"name":"Closet 1","order":628,"parentId":380,"scrollX":819,"scrollY":461},
{"id":670,"expanded":true,"name":"Closet 2","order":629,"parentId":380,"scrollX":478,"scrollY":448.5},
{"id":671,"expanded":true,"name":"Cattle Stable","order":544,"parentId":445,"scrollX":819,"scrollY":461},
{"id":672,"expanded":true,"name":"Woodrot Path 2 (After)","order":572,"parentId":553,"scrollX":819,"scrollY":461},
{"id":673,"expanded":true,"name":"Marketplace","order":695,"parentId":462,"scrollX":819,"scrollY":461},
{"id":674,"expanded":false,"name":"Entry","order":812,"parentId":258,"scrollX":819,"scrollY":461},
{"id":675,"expanded":true,"name":"Magma Falls","order":813,"parentId":258,"scrollX":811,"scrollY":787},
{"id":676,"expanded":false,"name":"Volcanic Beach 1","order":820,"parentId":258,"scrollX":819,"scrollY":461},
{"id":677,"expanded":false,"name":"Volcanic Beach 2","order":837,"parentId":258,"scrollX":1629,"scrollY":453},
{"id":678,"expanded":true,"name":"Difficult Ascent","order":821,"parentId":258,"scrollX":811,"scrollY":461},
{"id":679,"expanded":true,"name":"Temple Entrance","order":838,"parentId":258,"scrollX":819,"scrollY":461},
{"id":680,"expanded":false,"name":"Volcanic Beach 3","order":853,"parentId":258,"scrollX":819,"scrollY":461},
{"id":681,"expanded":false,"name":"Obsidian Bridge","order":854,"parentId":258,"scrollX":819,"scrollY":461},
{"id":682,"expanded":false,"name":"Behind the Falls","order":814,"parentId":675,"scrollX":819,"scrollY":461},
{"id":683,"expanded":false,"name":"Magma Cavern 1","order":815,"parentId":675,"scrollX":819,"scrollY":461},
{"id":684,"expanded":false,"name":"Magma Cavern 2","order":816,"parentId":675,"scrollX":819,"scrollY":453},
{"id":685,"expanded":false,"name":"Magma Cavern 3","order":817,"parentId":675,"scrollX":811,"scrollY":787},
{"id":686,"expanded":false,"name":"Flame Elevator 1","order":819,"parentId":675,"scrollX":819,"scrollY":461},
{"id":687,"expanded":false,"name":"Magma Cavern 4","order":818,"parentId":675,"scrollX":819,"scrollY":461},
{"id":688,"expanded":false,"name":"Winding Peak 1","order":822,"parentId":678,"scrollX":819,"scrollY":461},
{"id":689,"expanded":false,"name":"Winding Peak 2","order":823,"parentId":678,"scrollX":819,"scrollY":461},
{"id":690,"expanded":false,"name":"Winding Peak 3","order":824,"parentId":678,"scrollX":819,"scrollY":461},
{"id":691,"expanded":false,"name":"Flame Elevator 2","order":825,"parentId":678,"scrollX":832,"scrollY":640},
{"id":692,"expanded":false,"name":"Winding Peak 4","order":826,"parentId":678,"scrollX":832,"scrollY":640},
{"id":693,"expanded":false,"name":"Winding Peak 5","order":827,"parentId":678,"scrollX":819,"scrollY":461},
{"id":694,"expanded":false,"name":"Winding Peak 6","order":828,"parentId":678,"scrollX":832,"scrollY":640},
{"id":695,"expanded":true,"name":"Winding Peak 7","order":829,"parentId":678,"scrollX":819,"scrollY":461},
{"id":696,"expanded":false,"name":"Winding Peak 7 (After)","order":830,"parentId":695,"scrollX":819,"scrollY":461},
{"id":697,"expanded":false,"name":"Winding Peak 8","order":831,"parentId":678,"scrollX":832,"scrollY":640},
{"id":698,"expanded":false,"name":"Winding Peak 9","order":832,"parentId":678,"scrollX":819,"scrollY":461},
{"id":699,"expanded":false,"name":"Winding Peak 10","order":833,"parentId":678,"scrollX":819,"scrollY":461},
{"id":700,"expanded":false,"name":"Winding Peak 11","order":834,"parentId":678,"scrollX":819,"scrollY":461},
{"id":701,"expanded":true,"name":"Winding Peak 12","order":835,"parentId":678,"scrollX":819,"scrollY":461},
{"id":702,"expanded":false,"name":"Winding Peak 12 (After)","order":836,"parentId":701,"scrollX":819,"scrollY":461},
{"id":703,"expanded":false,"name":"Dirty Tunnel 1","order":847,"parentId":262,"scrollX":819,"scrollY":461},
{"id":704,"expanded":false,"name":"Dirty Tunnel 2","order":848,"parentId":262,"scrollX":832,"scrollY":640},
{"id":705,"expanded":true,"name":"Secret Entrance","order":845,"parentId":262,"scrollX":819,"scrollY":461},
{"id":706,"expanded":false,"name":"Dirty Tunnel 3","order":849,"parentId":262,"scrollX":819,"scrollY":461},
{"id":707,"expanded":false,"name":"Dirty Tunnel 4","order":850,"parentId":262,"scrollX":832,"scrollY":640},
{"id":708,"expanded":false,"name":"Dirty Tunnel 5","order":851,"parentId":262,"scrollX":819,"scrollY":461},
{"id":709,"expanded":false,"name":"Dirty Tunnel 6","order":852,"parentId":262,"scrollX":819,"scrollY":461},
{"id":710,"expanded":false,"name":"Secret Entrance (After)","order":846,"parentId":705,"scrollX":819,"scrollY":461},
{"id":711,"expanded":true,"name":"West Wing Bridge","order":797,"parentId":257,"scrollX":811,"scrollY":461},
{"id":712,"expanded":true,"name":"East Wing Bridge","order":805,"parentId":257,"scrollX":819,"scrollY":461},
{"id":713,"expanded":true,"name":"West Wing Hall","order":798,"parentId":711,"scrollX":811,"scrollY":787},
{"id":714,"expanded":true,"name":"Patio & Balcony","order":799,"parentId":713,"scrollX":811,"scrollY":500},
{"id":715,"expanded":true,"name":"Old Bedroom","order":800,"parentId":713,"scrollX":819,"scrollY":461},
{"id":716,"expanded":true,"name":"Sitting Room","order":801,"parentId":713,"scrollX":819,"scrollY":461},
{"id":717,"expanded":true,"name":"Pit Stairs","order":802,"parentId":716,"scrollX":819,"scrollY":461},
{"id":718,"expanded":true,"name":"Soulgem Pit","order":803,"parentId":716,"scrollX":821,"scrollY":461},
{"id":719,"expanded":true,"name":"Dora Markos' Vision","order":671,"parentId":615,"scrollX":819,"scrollY":461},
{"id":720,"expanded":true,"name":"New Rokkas Entrance (Scene)","order":248,"parentId":178,"scrollX":819,"scrollY":461},
{"id":721,"expanded":true,"name":"New Rokkas Entrance (After)","order":249,"parentId":178,"scrollX":819,"scrollY":461},
{"id":722,"expanded":true,"name":"New Rokkas North (Scene)","order":257,"parentId":181,"scrollX":819,"scrollY":461},
{"id":723,"expanded":true,"name":"Realm of Mischief","order":24,"parentId":1,"scrollX":819,"scrollY":461},
{"id":724,"expanded":true,"name":"Gianna Forest M","order":25,"parentId":723,"scrollX":816,"scrollY":1262},
{"id":725,"expanded":true,"name":"Sea Market M","order":26,"parentId":723,"scrollX":811,"scrollY":1459},
{"id":726,"expanded":true,"name":"East Wing Hall","order":806,"parentId":712,"scrollX":811,"scrollY":461},
{"id":727,"expanded":true,"name":"Dining Room","order":807,"parentId":726,"scrollX":819,"scrollY":461},
{"id":728,"expanded":true,"name":"Kitchen","order":808,"parentId":726,"scrollX":819,"scrollY":461},
{"id":729,"expanded":true,"name":"Library","order":809,"parentId":726,"scrollX":819,"scrollY":461},
{"id":730,"expanded":false,"name":"Temple Path","order":839,"parentId":679,"scrollX":811,"scrollY":461},
{"id":731,"expanded":true,"name":"Temple of Lust","order":840,"parentId":679,"scrollX":811,"scrollY":453},
{"id":732,"expanded":false,"name":"Lust's Castle Entry","order":843,"parentId":679,"scrollX":819,"scrollY":461},
{"id":733,"expanded":true,"name":"Tentacle Garden","order":841,"parentId":731,"scrollX":819,"scrollY":461},
{"id":734,"expanded":false,"name":"Tentacle Garden (Open)","order":842,"parentId":733,"scrollX":819,"scrollY":461},
{"id":735,"expanded":true,"name":"Lust's Castle","order":855,"parentId":258,"scrollX":819,"scrollY":461},
{"id":736,"expanded":true,"name":"Castle Foyer","order":856,"parentId":735,"scrollX":811,"scrollY":787},
{"id":737,"expanded":false,"name":"Hall of Challenges","order":860,"parentId":735,"scrollX":1629,"scrollY":453},
{"id":738,"expanded":true,"name":"Rokkas Plains M","order":27,"parentId":723,"scrollX":811,"scrollY":1459},
{"id":739,"expanded":true,"name":"Tabnath Mountains M","order":28,"parentId":723,"scrollX":811,"scrollY":1431},
{"id":740,"expanded":true,"name":"Woodrot Forest M","order":29,"parentId":723,"scrollX":811,"scrollY":1459},
{"id":741,"expanded":true,"name":"West Beach M","order":30,"parentId":723,"scrollX":811,"scrollY":1459},
{"id":742,"expanded":true,"name":"Forsaken Tower M","order":31,"parentId":723,"scrollX":811,"scrollY":621},
{"id":743,"expanded":true,"name":"Cathedral of the Spirit M","order":32,"parentId":723,"scrollX":811,"scrollY":1459},
{"id":744,"expanded":true,"name":"New Rokkas M","order":33,"parentId":723,"scrollX":811,"scrollY":1459},
{"id":745,"expanded":true,"name":"Tabnath M","order":34,"parentId":723,"scrollX":811,"scrollY":1459},
{"id":746,"expanded":true,"name":"Alisha's House M","order":35,"parentId":723,"scrollX":811,"scrollY":781},
{"id":747,"expanded":true,"name":"Bura's Travelling Circus M","order":36,"parentId":723,"scrollX":811,"scrollY":461},
{"id":748,"expanded":true,"name":"Chateau d'Yterre M","order":37,"parentId":723,"scrollX":811,"scrollY":1459},
{"id":749,"expanded":true,"name":"Vemix's Laboratory M","order":38,"parentId":723,"scrollX":811,"scrollY":1459},
{"id":750,"expanded":true,"name":"Kepiat Gallery M","order":39,"parentId":723,"scrollX":811,"scrollY":1459},
{"id":751,"expanded":true,"name":"Mt. Pleasant M","order":40,"parentId":723,"scrollX":811,"scrollY":1459},
{"id":752,"expanded":true,"name":"Phantom Express M","order":41,"parentId":723,"scrollX":811,"scrollY":1459},
{"id":753,"expanded":true,"name":"Tomb of Luxatep M","order":42,"parentId":723,"scrollX":811,"scrollY":461},
{"id":754,"expanded":true,"name":"City of Mist M","order":43,"parentId":723,"scrollX":811,"scrollY":462},
{"id":755,"expanded":true,"name":"Castle Hargrave M","order":44,"parentId":723,"scrollX":811,"scrollY":461},
{"id":756,"expanded":true,"name":"Demons' Spire M","order":45,"parentId":723,"scrollX":811,"scrollY":1459},
{"id":757,"expanded":true,"name":"Boss Challenge I","order":46,"parentId":723,"scrollX":811,"scrollY":461},
{"id":758,"expanded":true,"name":"Boss Challenge II","order":47,"parentId":723,"scrollX":811,"scrollY":461},
{"id":759,"expanded":true,"name":"Boss Challenge III","order":48,"parentId":723,"scrollX":811,"scrollY":461},
{"id":760,"expanded":true,"name":"Boss Challenge IV","order":49,"parentId":723,"scrollX":811,"scrollY":461},
{"id":761,"expanded":true,"name":"Boss Rush","order":50,"parentId":723,"scrollX":811,"scrollY":461},
{"id":762,"expanded":true,"name":"Demons' Peak","order":861,"parentId":735,"scrollX":819,"scrollY":461},
{"id":763,"expanded":false,"name":"Final Ends","order":862,"parentId":0,"scrollX":819,"scrollY":461},
{"id":764,"expanded":true,"name":"Moat","order":863,"parentId":763,"scrollX":832,"scrollY":640},
{"id":765,"expanded":true,"name":"Gianna Plaza","order":866,"parentId":763,"scrollX":1445,"scrollY":454},
{"id":766,"expanded":true,"name":"Courtyard","order":873,"parentId":763,"scrollX":478,"scrollY":448.5},
{"id":767,"expanded":true,"name":"Gianna Castle","order":874,"parentId":763,"scrollX":819,"scrollY":461},
{"id":768,"expanded":true,"name":"Hall of Orbs","order":875,"parentId":767,"scrollX":819,"scrollY":461},
{"id":769,"expanded":true,"name":"Stairwell","order":879,"parentId":763,"scrollX":817,"scrollY":455.5},
{"id":770,"expanded":true,"name":"Lyra's Manor","order":867,"parentId":765,"scrollX":819,"scrollY":461},
{"id":771,"expanded":true,"name":"Prime Minister's Office","order":880,"parentId":769,"scrollX":832,"scrollY":640},
{"id":772,"expanded":true,"name":"Residential Area","order":868,"parentId":765,"scrollX":819,"scrollY":461},
{"id":773,"expanded":true,"name":"Gatehouse","order":864,"parentId":764,"scrollX":478,"scrollY":448.5},
{"id":774,"expanded":true,"name":"Warp House","order":869,"parentId":772,"scrollX":819,"scrollY":461},
{"id":775,"expanded":true,"name":"Moat (Scene)","order":865,"parentId":764,"scrollX":819,"scrollY":461},
{"id":776,"expanded":false,"name":"Warp Room","order":870,"parentId":774,"scrollX":478,"scrollY":448.5},
{"id":777,"expanded":true,"name":"Windmill 7","order":871,"parentId":774,"scrollX":819,"scrollY":461},
{"id":778,"expanded":false,"name":"Windmill Top","order":872,"parentId":774,"scrollX":832,"scrollY":640},
{"id":779,"expanded":true,"name":"Throne Room","order":883,"parentId":763,"scrollX":819,"scrollY":461},
{"id":780,"expanded":true,"name":"Gianna Castle (After)","order":877,"parentId":767,"scrollX":478,"scrollY":448.5},
{"id":781,"expanded":true,"name":"Manor Foyer","order":71,"parentId":457,"scrollX":832,"scrollY":640},
{"id":782,"expanded":true,"name":"Manor Library","order":73,"parentId":457,"scrollX":819,"scrollY":461},
{"id":783,"expanded":true,"name":"Manor Gallery","order":72,"parentId":457,"scrollX":819,"scrollY":461},
{"id":784,"expanded":true,"name":"Torture Chamber","order":857,"parentId":736,"scrollX":819,"scrollY":461},
{"id":785,"expanded":false,"name":"Torture Chamber (After)","order":858,"parentId":784,"scrollX":819,"scrollY":461},
{"id":786,"expanded":true,"name":"Slave Storage","order":859,"parentId":736,"scrollX":819,"scrollY":461},
{"id":787,"expanded":false,"name":"Windmill Top (FE2)","order":890,"parentId":763,"scrollX":819,"scrollY":461},
{"id":788,"expanded":true,"name":"Hall of Orbs (Scene)","order":891,"parentId":763,"scrollX":819,"scrollY":461},
{"id":789,"expanded":true,"name":"FallingScene","order":884,"parentId":779,"scrollX":819,"scrollY":461},
{"id":790,"expanded":true,"name":"Throne Room (FE1)","order":885,"parentId":779,"scrollX":819,"scrollY":461},
{"id":791,"expanded":true,"name":"Venturas' House","order":118,"parentId":37,"scrollX":478,"scrollY":448.5},
{"id":792,"expanded":true,"name":"Lyra's Bedroom","order":74,"parentId":457,"scrollX":819,"scrollY":461},
{"id":793,"expanded":true,"name":"Throne Room (Scene)","order":783,"parentId":261,"scrollX":819,"scrollY":461},
{"id":794,"expanded":true,"name":"Forestkin Tent","order":369,"parentId":166,"scrollX":811,"scrollY":461},
{"id":795,"expanded":true,"name":"Klara's Cave","order":373,"parentId":167,"scrollX":819,"scrollY":461},
{"id":796,"expanded":true,"name":"Mt. Pleasant (BAD END)","order":576,"parentId":239,"scrollX":819,"scrollY":461},
{"id":797,"expanded":true,"name":"Lewd Bandit Hideout","order":126,"parentId":43,"scrollX":832,"scrollY":640},
{"id":798,"expanded":true,"name":"Stairwell (FE4)","order":882,"parentId":769,"scrollX":478,"scrollY":448.5},
{"id":799,"expanded":true,"name":"Prime Minister's Office (FE4)","order":881,"parentId":771,"scrollX":819,"scrollY":461},
{"id":800,"expanded":true,"name":"Gianna Castle (FE4)","order":878,"parentId":767,"scrollX":819,"scrollY":461},
{"id":801,"expanded":true,"name":"Hall of Orbs (FE4)","order":876,"parentId":768,"scrollX":819,"scrollY":461},
{"id":802,"expanded":true,"name":"Mt. Pleasant Entrance","order":577,"parentId":796,"scrollX":819,"scrollY":461},
{"id":803,"expanded":true,"name":"Mt. Pleasant Left 1","order":578,"parentId":796,"scrollX":819,"scrollY":461},
{"id":804,"expanded":true,"name":"Mt. Pleasant Left 2","order":579,"parentId":796,"scrollX":832,"scrollY":640},
{"id":805,"expanded":true,"name":"Mt. Pleasant Left 3","order":580,"parentId":796,"scrollX":832,"scrollY":640},
{"id":806,"expanded":true,"name":"Mt. Pleasant Right 1","order":581,"parentId":796,"scrollX":832,"scrollY":640},
{"id":807,"expanded":true,"name":"Mt. Pleasant Right 2","order":582,"parentId":796,"scrollX":819,"scrollY":461},
{"id":808,"expanded":true,"name":"Mt. Pleasant Right 3","order":584,"parentId":796,"scrollX":819,"scrollY":461},
{"id":809,"expanded":true,"name":"Farmland Entrance","order":586,"parentId":796,"scrollX":819,"scrollY":461},
{"id":810,"expanded":false,"name":"Mt. Pleasant Right 4","order":587,"parentId":796,"scrollX":811,"scrollY":461},
{"id":811,"expanded":true,"name":"Cattle Stable","order":585,"parentId":808,"scrollX":819,"scrollY":461},
{"id":812,"expanded":true,"name":"Item Shop","order":583,"parentId":807,"scrollX":819,"scrollY":461},
{"id":813,"expanded":true,"name":"Uphill Path 3","order":588,"parentId":796,"scrollX":819,"scrollY":461},
{"id":814,"expanded":true,"name":"City of Mist (BAD END)","order":725,"parentId":250,"scrollX":819,"scrollY":461},
{"id":815,"expanded":false,"name":"Tower Study","order":726,"parentId":814,"scrollX":832,"scrollY":640},
{"id":816,"expanded":true,"name":"Tower Foyer","order":727,"parentId":814,"scrollX":819,"scrollY":461},
{"id":817,"expanded":true,"name":"Tower Entry","order":728,"parentId":814,"scrollX":819,"scrollY":461},
{"id":818,"expanded":true,"name":"Bridge 1","order":729,"parentId":814,"scrollX":819,"scrollY":461},
{"id":819,"expanded":true,"name":"City View","order":730,"parentId":814,"scrollX":819,"scrollY":461},
{"id":820,"expanded":true,"name":"Elemental Classroom","order":94,"parentId":868,"scrollX":819,"scrollY":461},
{"id":821,"expanded":true,"name":"Throne Room (FE3) (Before)","order":887,"parentId":246,"scrollX":819,"scrollY":461},
{"id":822,"expanded":true,"name":"FE 3 World Map","order":888,"parentId":246,"scrollX":869,"scrollY":454},
{"id":823,"expanded":true,"name":"West Beach 1","order":480,"parentId":235,"scrollX":819,"scrollY":461},
{"id":824,"expanded":true,"name":"West Beach Cattle Ranch","order":471,"parentId":485,"scrollX":478,"scrollY":448.5},
{"id":825,"expanded":true,"name":"Passenger Car (BAD END)","order":677,"parentId":247,"scrollX":819,"scrollY":461},
{"id":826,"expanded":true,"name":"Throne Room (Scene)(FE1)","order":784,"parentId":261,"scrollX":478,"scrollY":448.5},
{"id":827,"expanded":true,"name":"West Beach 2","order":481,"parentId":235,"scrollX":819,"scrollY":461},
{"id":828,"expanded":true,"name":"Chalet Entrance","order":482,"parentId":827,"scrollX":819,"scrollY":461},
{"id":829,"expanded":true,"name":"Chalet Dock","order":484,"parentId":827,"scrollX":819,"scrollY":461},
{"id":830,"expanded":true,"name":"Seaside Chalet","order":483,"parentId":828,"scrollX":819,"scrollY":453},
{"id":831,"expanded":true,"name":"West Beach 3","order":485,"parentId":235,"scrollX":819,"scrollY":461},
{"id":832,"expanded":true,"name":"West Beach Desert","order":486,"parentId":235,"scrollX":821,"scrollY":461},
{"id":833,"expanded":true,"name":"West Beach 4","order":487,"parentId":235,"scrollX":819,"scrollY":461},
{"id":834,"expanded":true,"name":"Great Hall","order":767,"parentId":256,"scrollX":2453,"scrollY":625},
{"id":835,"expanded":true,"name":"Hallway","order":772,"parentId":256,"scrollX":819,"scrollY":461},
{"id":836,"expanded":true,"name":"Workshop Hallway","order":773,"parentId":256,"scrollX":811,"scrollY":461},
{"id":837,"expanded":true,"name":"Maharani's Door","order":774,"parentId":836,"scrollX":819,"scrollY":461},
{"id":838,"expanded":true,"name":"Acolyte's Quarters 1","order":768,"parentId":834,"scrollX":819,"scrollY":461},
{"id":839,"expanded":true,"name":"Acolyte's Quarters 2","order":769,"parentId":834,"scrollX":819,"scrollY":461},
{"id":840,"expanded":true,"name":"Acolyte's Quarters 3","order":770,"parentId":834,"scrollX":819,"scrollY":461},
{"id":841,"expanded":true,"name":"Acolyte's Quarters 4","order":771,"parentId":834,"scrollX":819,"scrollY":461},
{"id":842,"expanded":true,"name":"Workshop 1","order":776,"parentId":836,"scrollX":338,"scrollY":448.5},
{"id":843,"expanded":true,"name":"Workshop 2","order":777,"parentId":836,"scrollX":819,"scrollY":461},
{"id":844,"expanded":true,"name":"Workshop 3","order":778,"parentId":836,"scrollX":819,"scrollY":461},
{"id":845,"expanded":true,"name":"Mini Tunnel","order":779,"parentId":836,"scrollX":811,"scrollY":461},
{"id":846,"expanded":true,"name":"Maharani's Workbench","order":775,"parentId":837,"scrollX":819,"scrollY":461},
{"id":847,"expanded":true,"name":"Puppet Storage","order":780,"parentId":836,"scrollX":819,"scrollY":461},
{"id":848,"expanded":true,"name":"Wu'Ka's Vision","order":672,"parentId":615,"scrollX":819,"scrollY":461},
{"id":849,"expanded":true,"name":"Mage's Univerity Entry","order":78,"parentId":22,"scrollX":811,"scrollY":461},
{"id":850,"expanded":true,"name":"Marriage Scene","order":281,"parentId":95,"scrollX":811,"scrollY":461},
{"id":851,"expanded":false,"name":"Forest Cabin F2","order":188,"parentId":90,"scrollX":819,"scrollY":461},
{"id":852,"expanded":true,"name":"East Tower Entry","order":87,"parentId":849,"scrollX":819,"scrollY":461},
{"id":853,"expanded":true,"name":"Front Entry","order":79,"parentId":849,"scrollX":811,"scrollY":787},
{"id":854,"expanded":true,"name":"Aribelle's Office","order":81,"parentId":853,"scrollX":819,"scrollY":461},
{"id":855,"expanded":true,"name":"Lisse's Office","order":82,"parentId":853,"scrollX":819,"scrollY":461},
{"id":856,"expanded":true,"name":"Front Entry (Open)","order":80,"parentId":853,"scrollX":811,"scrollY":461},
{"id":857,"expanded":true,"name":"Elemental Studies","order":84,"parentId":638,"scrollX":819,"scrollY":461},
{"id":858,"expanded":true,"name":"Alchemical Studies","order":85,"parentId":638,"scrollX":819,"scrollY":461},
{"id":859,"expanded":true,"name":"Hypnotic Studies","order":88,"parentId":852,"scrollX":819,"scrollY":461},
{"id":860,"expanded":true,"name":"Transformative Studies","order":89,"parentId":852,"scrollX":819,"scrollY":461},
{"id":861,"expanded":true,"name":"The Under-Study","order":91,"parentId":849,"scrollX":819,"scrollY":461},
{"id":862,"expanded":true,"name":"Landing","order":92,"parentId":861,"scrollX":819,"scrollY":461},
{"id":863,"expanded":true,"name":"Arachne Path 1","order":377,"parentId":172,"scrollX":832,"scrollY":640},
{"id":864,"expanded":true,"name":"The Under-Study M","order":52,"parentId":723,"scrollX":811,"scrollY":1459},
{"id":865,"expanded":true,"name":"Valua M","order":53,"parentId":723,"scrollX":811,"scrollY":461},
{"id":866,"expanded":true,"name":"Villa da Vici M","order":54,"parentId":723,"scrollX":811,"scrollY":461},
{"id":867,"expanded":true,"name":"Urverk M","order":55,"parentId":723,"scrollX":811,"scrollY":1459},
{"id":868,"expanded":true,"name":"Hallway 1","order":93,"parentId":861,"scrollX":811,"scrollY":461},
{"id":869,"expanded":true,"name":"Hallway 2","order":98,"parentId":861,"scrollX":811,"scrollY":787},
{"id":870,"expanded":true,"name":"Dock (Early)","order":796,"parentId":249,"scrollX":819,"scrollY":461},
{"id":871,"expanded":true,"name":"Hargrave Courtyard (Early)","order":794,"parentId":493,"scrollX":811,"scrollY":461},
{"id":872,"expanded":true,"name":"Upper Courtyard (Early)","order":792,"parentId":496,"scrollX":811,"scrollY":461},
{"id":873,"expanded":true,"name":"West Wing Bridge (Early)","order":804,"parentId":711,"scrollX":819,"scrollY":461},
{"id":874,"expanded":true,"name":"East Wing Bridge (Early)","order":810,"parentId":712,"scrollX":819,"scrollY":461},
{"id":875,"expanded":true,"name":"Alchemical Classroom","order":95,"parentId":868,"scrollX":819,"scrollY":461},
{"id":876,"expanded":true,"name":"Hypnotic Classroom","order":96,"parentId":868,"scrollX":819,"scrollY":461},
{"id":877,"expanded":true,"name":"Transformative Classroom","order":97,"parentId":868,"scrollX":811,"scrollY":461},
{"id":878,"expanded":true,"name":"Spellball Field","order":104,"parentId":849,"scrollX":819,"scrollY":461},
{"id":879,"expanded":true,"name":"Lab","order":99,"parentId":869,"scrollX":811,"scrollY":615},
{"id":880,"expanded":true,"name":"Library","order":100,"parentId":869,"scrollX":811,"scrollY":461},
{"id":881,"expanded":true,"name":"Isabella da Vici's Vision","order":673,"parentId":615,"scrollX":819,"scrollY":461},
{"id":882,"expanded":true,"name":"Arachne Path 2","order":378,"parentId":172,"scrollX":832,"scrollY":640},
{"id":883,"expanded":true,"name":"Arachne Path 3","order":380,"parentId":172,"scrollX":819,"scrollY":461},
{"id":884,"expanded":true,"name":"Arachne Path 2 (Open)","order":379,"parentId":882,"scrollX":819,"scrollY":461},
{"id":885,"expanded":true,"name":"Arachne Path 4","order":381,"parentId":172,"scrollX":819,"scrollY":461},
{"id":886,"expanded":true,"name":"West Tower Dormitory","order":86,"parentId":638,"scrollX":819,"scrollY":461},
{"id":887,"expanded":true,"name":"East Tower Dormitory","order":90,"parentId":852,"scrollX":819,"scrollY":461},
{"id":888,"expanded":true,"name":"Under-Under-Study","order":101,"parentId":869,"scrollX":819,"scrollY":461},
{"id":889,"expanded":true,"name":"Hallway 2 (Open)","order":102,"parentId":869,"scrollX":811,"scrollY":615},
{"id":890,"expanded":true,"name":"Conditioning Room","order":103,"parentId":861,"scrollX":819,"scrollY":461},
{"id":891,"expanded":true,"name":"Lilina's Island (FE5)","order":892,"parentId":763,"scrollX":819,"scrollY":461},
null,
{"id":893,"expanded":false,"name":"Forest Cabin Cellar","order":189,"parentId":90,"scrollX":819,"scrollY":461}
]